{
"meta":{"test_sets":[],"test_metrics":[],"learn_metrics":[{"best_value":"Min","name":"MultiClass"}],"launch_mode":"Train","parameters":"","iteration_count":1000,"learn_sets":["learn"],"name":"experiment"},
"iterations":[
{"learn":[1.783725539],"iteration":0,"passed_time":5.536917647,"remaining_time":5531.38073},
{"learn":[1.578054794],"iteration":1,"passed_time":9.051562768,"remaining_time":4516.729821},
{"learn":[1.411162484],"iteration":2,"passed_time":12.80601502,"remaining_time":4255.865658},
{"learn":[1.302815204],"iteration":3,"passed_time":14.89882686,"remaining_time":3709.807887},
{"learn":[1.192657383],"iteration":4,"passed_time":18.83813338,"remaining_time":3748.788543},
{"learn":[1.105278982],"iteration":5,"passed_time":22.30696439,"remaining_time":3695.520435},
{"learn":[1.03761005],"iteration":6,"passed_time":26.20112732,"remaining_time":3716.817061},
{"learn":[0.9787206964],"iteration":7,"passed_time":30.21083526,"remaining_time":3746.143572},
{"learn":[0.9277718839],"iteration":8,"passed_time":33.99656922,"remaining_time":3743.400011},
{"learn":[0.8868195689],"iteration":9,"passed_time":37.74415591,"remaining_time":3736.671435},
{"learn":[0.8507236947],"iteration":10,"passed_time":41.02468197,"remaining_time":3688.491861},
{"learn":[0.8163409327],"iteration":11,"passed_time":44.49485157,"remaining_time":3663.409446},
{"learn":[0.785631021],"iteration":12,"passed_time":47.76023617,"remaining_time":3626.104085},
{"learn":[0.7592916671],"iteration":13,"passed_time":50.84670807,"remaining_time":3581.061011},
{"learn":[0.733818248],"iteration":14,"passed_time":53.9426705,"remaining_time":3542.235363},
{"learn":[0.712135023],"iteration":15,"passed_time":57.02397979,"remaining_time":3506.974757},
{"learn":[0.693075828],"iteration":16,"passed_time":60.119057,"remaining_time":3476.296061},
{"learn":[0.6747357436],"iteration":17,"passed_time":63.45899538,"remaining_time":3462.040748},
{"learn":[0.6597251147],"iteration":18,"passed_time":66.55477032,"remaining_time":3436.327878},
{"learn":[0.6451517333],"iteration":19,"passed_time":69.59513169,"remaining_time":3410.161453},
{"learn":[0.6320649367],"iteration":20,"passed_time":73.06812046,"remaining_time":3406.366187},
{"learn":[0.6202182562],"iteration":21,"passed_time":76.44839069,"remaining_time":3398.478459},
{"learn":[0.6100343553],"iteration":22,"passed_time":79.65757292,"remaining_time":3383.715163},
{"learn":[0.6000709378],"iteration":23,"passed_time":83.01129111,"remaining_time":3375.792505},
{"learn":[0.5904606334],"iteration":24,"passed_time":86.34162363,"remaining_time":3367.323322},
{"learn":[0.583268563],"iteration":25,"passed_time":90.15160366,"remaining_time":3377.217768},
{"learn":[0.5752091919],"iteration":26,"passed_time":93.93397157,"remaining_time":3385.102012},
{"learn":[0.5647952734],"iteration":27,"passed_time":96.97488582,"remaining_time":3366.413894},
{"learn":[0.5580122711],"iteration":28,"passed_time":100.1039254,"remaining_time":3351.75557},
{"learn":[0.5522947177],"iteration":29,"passed_time":104.1326495,"remaining_time":3366.955668},
{"learn":[0.5464297884],"iteration":30,"passed_time":108.0025193,"remaining_time":3375.949717},
{"learn":[0.5411205355],"iteration":31,"passed_time":111.8694147,"remaining_time":3384.049796},
{"learn":[0.5364358859],"iteration":32,"passed_time":115.8338575,"remaining_time":3394.283036},
{"learn":[0.5304898861],"iteration":33,"passed_time":119.043448,"remaining_time":3382.234433},
{"learn":[0.5255947682],"iteration":34,"passed_time":122.1784098,"remaining_time":3368.633299},
{"learn":[0.52127683],"iteration":35,"passed_time":125.1512653,"remaining_time":3351.27277},
{"learn":[0.5175026408],"iteration":36,"passed_time":128.5819882,"remaining_time":3346.606883},
{"learn":[0.5132375015],"iteration":37,"passed_time":131.7458433,"remaining_time":3335.250033},
{"learn":[0.5108200156],"iteration":38,"passed_time":135.8726416,"remaining_time":3348.041246},
{"learn":[0.5081631893],"iteration":39,"passed_time":139.9893394,"remaining_time":3359.744146},
{"learn":[0.5045513981],"iteration":40,"passed_time":143.1599188,"remaining_time":3348.545417},
{"learn":[0.503158593],"iteration":41,"passed_time":147.4070915,"remaining_time":3362.285564},
{"learn":[0.5000691926],"iteration":42,"passed_time":151.3571847,"remaining_time":3368.577343},
{"learn":[0.4971257862],"iteration":43,"passed_time":155.3663704,"remaining_time":3375.687502},
{"learn":[0.4947078699],"iteration":44,"passed_time":159.2855236,"remaining_time":3380.392779},
{"learn":[0.491842356],"iteration":45,"passed_time":162.9313089,"remaining_time":3379.053666},
{"learn":[0.4895121283],"iteration":46,"passed_time":166.29979,"remaining_time":3371.993615},
{"learn":[0.4878114834],"iteration":47,"passed_time":170.1075256,"remaining_time":3373.799258},
{"learn":[0.4850263202],"iteration":48,"passed_time":173.9849752,"remaining_time":3376.728804},
{"learn":[0.4831846207],"iteration":49,"passed_time":177.9504147,"remaining_time":3381.05788},
{"learn":[0.4806554446],"iteration":50,"passed_time":182.100483,"remaining_time":3388.497223},
{"learn":[0.4783515295],"iteration":51,"passed_time":185.9986246,"remaining_time":3390.898002},
{"learn":[0.4767030437],"iteration":52,"passed_time":189.5888589,"remaining_time":3387.559421},
{"learn":[0.4742117933],"iteration":53,"passed_time":193.1307489,"remaining_time":3383.364601},
{"learn":[0.4718014765],"iteration":54,"passed_time":196.809634,"remaining_time":3381.547349},
{"learn":[0.4699631393],"iteration":55,"passed_time":200.0230132,"remaining_time":3371.816508},
{"learn":[0.4682217736],"iteration":56,"passed_time":203.9324357,"remaining_time":3373.829594},
{"learn":[0.4656518435],"iteration":57,"passed_time":207.570127,"remaining_time":3371.225166},
{"learn":[0.4641133659],"iteration":58,"passed_time":211.2760253,"remaining_time":3369.673556},
{"learn":[0.4619079068],"iteration":59,"passed_time":215.0110846,"remaining_time":3368.506992},
{"learn":[0.4603403978],"iteration":60,"passed_time":218.8726454,"remaining_time":3369.203508},
{"learn":[0.459016695],"iteration":61,"passed_time":222.1734842,"remaining_time":3361.269809},
{"learn":[0.4580076674],"iteration":62,"passed_time":226.2763273,"remaining_time":3365.411407},
{"learn":[0.4553095543],"iteration":63,"passed_time":229.4693058,"remaining_time":3355.988597},
{"learn":[0.4536050794],"iteration":64,"passed_time":233.1544362,"remaining_time":3353.836889},
{"learn":[0.452814937],"iteration":65,"passed_time":237.4840134,"remaining_time":3360.758614},
{"learn":[0.4515902616],"iteration":66,"passed_time":241.1426857,"remaining_time":3358.001876},
{"learn":[0.4502990437],"iteration":67,"passed_time":244.8624626,"remaining_time":3356.056105},
{"learn":[0.4496115667],"iteration":68,"passed_time":248.9464157,"remaining_time":3358.972652},
{"learn":[0.4485016267],"iteration":69,"passed_time":253.0476178,"remaining_time":3361.918351},
{"learn":[0.447233042],"iteration":70,"passed_time":257.4222969,"remaining_time":3368.243856},
{"learn":[0.4463448989],"iteration":71,"passed_time":261.5424772,"remaining_time":3370.991929},
{"learn":[0.444948291],"iteration":72,"passed_time":265.2959676,"remaining_time":3368.895369},
{"learn":[0.4438003786],"iteration":73,"passed_time":268.9865157,"remaining_time":3365.966399},
{"learn":[0.4426364118],"iteration":74,"passed_time":273.2403029,"remaining_time":3369.963736},
{"learn":[0.4417227722],"iteration":75,"passed_time":277.330319,"remaining_time":3371.752825},
{"learn":[0.4403898263],"iteration":76,"passed_time":281.3185196,"remaining_time":3372.168748},
{"learn":[0.4393742426],"iteration":77,"passed_time":285.9205551,"remaining_time":3379.727587},
{"learn":[0.4385876194],"iteration":78,"passed_time":289.8848691,"remaining_time":3379.543853},
{"learn":[0.437572275],"iteration":79,"passed_time":293.4216125,"remaining_time":3374.348544},
{"learn":[0.4365697766],"iteration":80,"passed_time":297.0855408,"remaining_time":3370.637185},
{"learn":[0.4357097627],"iteration":81,"passed_time":301.7951588,"remaining_time":3378.633607},
{"learn":[0.4350619925],"iteration":82,"passed_time":306.2279524,"remaining_time":3383.26545},
{"learn":[0.4343342895],"iteration":83,"passed_time":310.2389464,"remaining_time":3383.081844},
{"learn":[0.4337310918],"iteration":84,"passed_time":314.7618154,"remaining_time":3388.318366},
{"learn":[0.4333818356],"iteration":85,"passed_time":319.7101637,"remaining_time":3397.849879},
{"learn":[0.4328587491],"iteration":86,"passed_time":324.5043361,"remaining_time":3405.430562},
{"learn":[0.4320780234],"iteration":87,"passed_time":328.3378216,"remaining_time":3402.773787},
{"learn":[0.4302352474],"iteration":88,"passed_time":331.5117907,"remaining_time":3393.33979},
{"learn":[0.4293914848],"iteration":89,"passed_time":335.6322297,"remaining_time":3393.614767},
{"learn":[0.4280966308],"iteration":90,"passed_time":339.4046508,"remaining_time":3390.316787},
{"learn":[0.4274178387],"iteration":91,"passed_time":342.8639205,"remaining_time":3383.917824},
{"learn":[0.4267132985],"iteration":92,"passed_time":346.956056,"remaining_time":3383.754223},
{"learn":[0.426161788],"iteration":93,"passed_time":350.7584565,"remaining_time":3380.714485},
{"learn":[0.4259968536],"iteration":94,"passed_time":355.219857,"remaining_time":3383.936532},
{"learn":[0.4255186709],"iteration":95,"passed_time":359.852266,"remaining_time":3388.608838},
{"learn":[0.4250529426],"iteration":96,"passed_time":364.2176403,"remaining_time":3390.603394},
{"learn":[0.4247379854],"iteration":97,"passed_time":368.1144567,"remaining_time":3388.15551},
{"learn":[0.4237646237],"iteration":98,"passed_time":371.9851289,"remaining_time":3385.440416},
{"learn":[0.4230192406],"iteration":99,"passed_time":375.6582621,"remaining_time":3380.924359},
{"learn":[0.4224523616],"iteration":100,"passed_time":379.7191293,"remaining_time":3379.876211},
{"learn":[0.4218254526],"iteration":101,"passed_time":383.7672395,"remaining_time":3378.656678},
{"learn":[0.4215001526],"iteration":102,"passed_time":387.1284019,"remaining_time":3371.399772},
{"learn":[0.4208977],"iteration":103,"passed_time":391.4846805,"remaining_time":3372.791093},
{"learn":[0.4197402022],"iteration":104,"passed_time":394.824354,"remaining_time":3365.407589},
{"learn":[0.4192933655],"iteration":105,"passed_time":399.550495,"remaining_time":3369.793797},
{"learn":[0.4189210496],"iteration":106,"passed_time":404.252765,"remaining_time":3373.810459},
{"learn":[0.4184322533],"iteration":107,"passed_time":408.8835505,"remaining_time":3377.07525},
{"learn":[0.4174847217],"iteration":108,"passed_time":411.9612902,"remaining_time":3367.500088},
{"learn":[0.4171152929],"iteration":109,"passed_time":415.7791392,"remaining_time":3364.031217},
{"learn":[0.4159794631],"iteration":110,"passed_time":419.2894235,"remaining_time":3358.09277},
{"learn":[0.4152416634],"iteration":111,"passed_time":423.0338673,"remaining_time":3354.054234},
{"learn":[0.4148280994],"iteration":112,"passed_time":426.7266545,"remaining_time":3349.615421},
{"learn":[0.4141247007],"iteration":113,"passed_time":431.2248003,"remaining_time":3351.448886},
{"learn":[0.4130464035],"iteration":114,"passed_time":435.2613014,"remaining_time":3349.61958},
{"learn":[0.4117080618],"iteration":115,"passed_time":438.3412596,"remaining_time":3340.462702},
{"learn":[0.4106481756],"iteration":116,"passed_time":441.4061314,"remaining_time":3331.295846},
{"learn":[0.4095353653],"iteration":117,"passed_time":445.2873342,"remaining_time":3328.334142},
{"learn":[0.4092347863],"iteration":118,"passed_time":449.1501163,"remaining_time":3325.220609},
{"learn":[0.4087543386],"iteration":119,"passed_time":453.4261749,"remaining_time":3325.125283},
{"learn":[0.4079768424],"iteration":120,"passed_time":457.2543969,"remaining_time":3321.707561},
{"learn":[0.4071889469],"iteration":121,"passed_time":460.6981459,"remaining_time":3315.516164},
{"learn":[0.4061556796],"iteration":122,"passed_time":463.8673576,"remaining_time":3307.411972},
{"learn":[0.405450613],"iteration":123,"passed_time":467.7225802,"remaining_time":3304.233712},
{"learn":[0.4050129885],"iteration":124,"passed_time":471.4889844,"remaining_time":3300.422891},
{"learn":[0.4042024047],"iteration":125,"passed_time":474.85768,"remaining_time":3293.854066},
{"learn":[0.4039564149],"iteration":126,"passed_time":479.6478746,"remaining_time":3297.107044},
{"learn":[0.4032906351],"iteration":127,"passed_time":483.7294262,"remaining_time":3295.406716},
{"learn":[0.4028244309],"iteration":128,"passed_time":487.6439266,"remaining_time":3292.541551},
{"learn":[0.4020784243],"iteration":129,"passed_time":491.1626917,"remaining_time":3287.01186},
{"learn":[0.401577842],"iteration":130,"passed_time":494.829299,"remaining_time":3282.493594},
{"learn":[0.4008400241],"iteration":131,"passed_time":498.3551731,"remaining_time":3277.062805},
{"learn":[0.4004143867],"iteration":132,"passed_time":502.7777218,"remaining_time":3277.505901},
{"learn":[0.3999156607],"iteration":133,"passed_time":506.8685653,"remaining_time":3275.732668},
{"learn":[0.399179292],"iteration":134,"passed_time":509.9893352,"remaining_time":3267.709444},
{"learn":[0.3988345612],"iteration":135,"passed_time":513.6588983,"remaining_time":3263.244766},
{"learn":[0.3983680127],"iteration":136,"passed_time":517.5828697,"remaining_time":3260.394282},
{"learn":[0.3979781998],"iteration":137,"passed_time":522.0139346,"remaining_time":3260.695736},
{"learn":[0.3974635257],"iteration":138,"passed_time":525.1601017,"remaining_time":3252.970126},
{"learn":[0.3962104209],"iteration":139,"passed_time":528.1285945,"remaining_time":3244.218509},
{"learn":[0.3957810216],"iteration":140,"passed_time":531.7765619,"remaining_time":3239.688416},
{"learn":[0.3951164664],"iteration":141,"passed_time":535.410726,"remaining_time":3235.087345},
{"learn":[0.3944467134],"iteration":142,"passed_time":539.340263,"remaining_time":3232.269968},
{"learn":[0.3941542459],"iteration":143,"passed_time":543.1157433,"remaining_time":3228.521363},
{"learn":[0.3936952718],"iteration":144,"passed_time":547.0455634,"remaining_time":3225.68246},
{"learn":[0.3935823338],"iteration":145,"passed_time":550.9180385,"remaining_time":3222.493184},
{"learn":[0.3933013124],"iteration":146,"passed_time":555.0685189,"remaining_time":3220.9078},
{"learn":[0.3928242432],"iteration":147,"passed_time":559.0864547,"remaining_time":3218.524726},
{"learn":[0.3920415297],"iteration":148,"passed_time":563.065967,"remaining_time":3215.900254},
{"learn":[0.3915872238],"iteration":149,"passed_time":566.3467394,"remaining_time":3209.29819},
{"learn":[0.3912979833],"iteration":150,"passed_time":570.267117,"remaining_time":3206.336307},
{"learn":[0.3907237163],"iteration":151,"passed_time":574.4626172,"remaining_time":3204.896706},
{"learn":[0.3901988144],"iteration":152,"passed_time":578.335117,"remaining_time":3201.632968},
{"learn":[0.3897936492],"iteration":153,"passed_time":581.8263531,"remaining_time":3196.266849},
{"learn":[0.3893269456],"iteration":154,"passed_time":585.181993,"remaining_time":3190.185704},
{"learn":[0.3888014813],"iteration":155,"passed_time":589.004589,"remaining_time":3186.665853},
{"learn":[0.3885349926],"iteration":156,"passed_time":593.2150734,"remaining_time":3185.224885},
{"learn":[0.3884836748],"iteration":157,"passed_time":597.967427,"remaining_time":3186.636541},
{"learn":[0.3881945511],"iteration":158,"passed_time":602.6440705,"remaining_time":3187.570209},
{"learn":[0.3877708414],"iteration":159,"passed_time":606.6692387,"remaining_time":3185.013503},
{"learn":[0.3875651855],"iteration":160,"passed_time":610.7170194,"remaining_time":3182.556393},
{"learn":[0.3873419939],"iteration":161,"passed_time":614.9856941,"remaining_time":3181.222294},
{"learn":[0.3872082391],"iteration":162,"passed_time":619.2865035,"remaining_time":3180.017199},
{"learn":[0.3868207989],"iteration":163,"passed_time":623.8449518,"remaining_time":3180.087681},
{"learn":[0.3866008361],"iteration":164,"passed_time":628.4054805,"remaining_time":3180.112583},
{"learn":[0.3863091331],"iteration":165,"passed_time":632.6755513,"remaining_time":3178.62295},
{"learn":[0.385914785],"iteration":166,"passed_time":637.5624927,"remaining_time":3180.176984},
{"learn":[0.3853801789],"iteration":167,"passed_time":640.6918176,"remaining_time":3172.949954},
{"learn":[0.3852431123],"iteration":168,"passed_time":644.9637571,"remaining_time":3171.389835},
{"learn":[0.3850009685],"iteration":169,"passed_time":649.3408088,"remaining_time":3170.311008},
{"learn":[0.3848086599],"iteration":170,"passed_time":653.1809663,"remaining_time":3166.590766},
{"learn":[0.3846389753],"iteration":171,"passed_time":657.2560808,"remaining_time":3164.000203},
{"learn":[0.3844879311],"iteration":172,"passed_time":660.5649228,"remaining_time":3157.729429},
{"learn":[0.3842478819],"iteration":173,"passed_time":664.7653345,"remaining_time":3155.725093},
{"learn":[0.3838898602],"iteration":174,"passed_time":669.2027409,"remaining_time":3154.812921},
{"learn":[0.3835327044],"iteration":175,"passed_time":673.0469013,"remaining_time":3151.08322},
{"learn":[0.3830742781],"iteration":176,"passed_time":676.4205632,"remaining_time":3145.16454},
{"learn":[0.3827548338],"iteration":177,"passed_time":680.716452,"remaining_time":3143.533278},
{"learn":[0.3821007798],"iteration":178,"passed_time":684.0224639,"remaining_time":3137.332083},
{"learn":[0.3818017542],"iteration":179,"passed_time":688.1391715,"remaining_time":3134.856226},
{"learn":[0.3815512765],"iteration":180,"passed_time":692.1643389,"remaining_time":3131.94803},
{"learn":[0.3813713859],"iteration":181,"passed_time":696.5098537,"remaining_time":3130.467365},
{"learn":[0.3812098067],"iteration":182,"passed_time":701.0982948,"remaining_time":3130.039928},
{"learn":[0.3809508205],"iteration":183,"passed_time":704.4179565,"remaining_time":3123.940503},
{"learn":[0.3806476955],"iteration":184,"passed_time":707.726601,"remaining_time":3117.822594},
{"learn":[0.3805128497],"iteration":185,"passed_time":711.929385,"remaining_time":3115.647954},
{"learn":[0.3801695665],"iteration":186,"passed_time":716.2566263,"remaining_time":3113.992712},
{"learn":[0.379660574],"iteration":187,"passed_time":720.0809909,"remaining_time":3110.137046},
{"learn":[0.3794417359],"iteration":188,"passed_time":724.6573141,"remaining_time":3109.508369},
{"learn":[0.3793116931],"iteration":189,"passed_time":728.502106,"remaining_time":3105.719504},
{"learn":[0.3791260404],"iteration":190,"passed_time":733.0169972,"remaining_time":3104.768329},
{"learn":[0.3789930261],"iteration":191,"passed_time":737.2903537,"remaining_time":3102.763572},
{"learn":[0.3784079073],"iteration":192,"passed_time":741.0443827,"remaining_time":3098.563818},
{"learn":[0.3781140246],"iteration":193,"passed_time":745.6391698,"remaining_time":3097.861706},
{"learn":[0.3779651912],"iteration":194,"passed_time":749.693361,"remaining_time":3094.887977},
{"learn":[0.3776175907],"iteration":195,"passed_time":753.5678611,"remaining_time":3091.166124},
{"learn":[0.3774561124],"iteration":196,"passed_time":757.5164495,"remaining_time":3087.744715},
{"learn":[0.37737218],"iteration":197,"passed_time":761.0619731,"remaining_time":3082.685366},
{"learn":[0.3772871548],"iteration":198,"passed_time":765.1264973,"remaining_time":3079.730273},
{"learn":[0.3772192814],"iteration":199,"passed_time":769.2201279,"remaining_time":3076.880512},
{"learn":[0.3770947319],"iteration":200,"passed_time":773.4626655,"remaining_time":3074.610297},
{"learn":[0.3767749294],"iteration":201,"passed_time":777.3384875,"remaining_time":3070.871847},
{"learn":[0.376583789],"iteration":202,"passed_time":781.5231258,"remaining_time":3068.344489},
{"learn":[0.3764483262],"iteration":203,"passed_time":786.0660284,"remaining_time":3067.198817},
{"learn":[0.3762618642],"iteration":204,"passed_time":790.1080565,"remaining_time":3064.077585},
{"learn":[0.3755796277],"iteration":205,"passed_time":794.3972434,"remaining_time":3061.900055},
{"learn":[0.375054963],"iteration":206,"passed_time":798.2859866,"remaining_time":3058.168055},
{"learn":[0.3749125841],"iteration":207,"passed_time":803.2977689,"remaining_time":3058.710735},
{"learn":[0.3744766491],"iteration":208,"passed_time":806.8003788,"remaining_time":3053.488515},
{"learn":[0.3744048616],"iteration":209,"passed_time":811.2537836,"remaining_time":3051.859472},
{"learn":[0.3742045155],"iteration":210,"passed_time":815.3917758,"remaining_time":3049.024223},
{"learn":[0.3736589437],"iteration":211,"passed_time":819.2261086,"remaining_time":3045.047989},
{"learn":[0.373446251],"iteration":212,"passed_time":822.9447404,"remaining_time":3040.64559},
{"learn":[0.3731525099],"iteration":213,"passed_time":827.6757313,"remaining_time":3039.967873},
{"learn":[0.3731019908],"iteration":214,"passed_time":832.5263529,"remaining_time":3039.689242},
{"learn":[0.372486937],"iteration":215,"passed_time":835.615734,"remaining_time":3032.975627},
{"learn":[0.3721033787],"iteration":216,"passed_time":839.6773893,"remaining_time":3029.803667},
{"learn":[0.3719771593],"iteration":217,"passed_time":844.6191938,"remaining_time":3029.780778},
{"learn":[0.371798488],"iteration":218,"passed_time":848.3952505,"remaining_time":3025.555665},
{"learn":[0.3716648414],"iteration":219,"passed_time":852.4614117,"remaining_time":3022.363187},
{"learn":[0.3712088426],"iteration":220,"passed_time":856.3767676,"remaining_time":3018.631231},
{"learn":[0.3711248223],"iteration":221,"passed_time":860.859949,"remaining_time":3016.887569},
{"learn":[0.371032742],"iteration":222,"passed_time":865.5775702,"remaining_time":3015.936197},
{"learn":[0.370841815],"iteration":223,"passed_time":869.6555264,"remaining_time":3012.735216},
{"learn":[0.370697426],"iteration":224,"passed_time":874.2848362,"remaining_time":3011.425547},
{"learn":[0.3706355723],"iteration":225,"passed_time":878.3697006,"remaining_time":3008.221895},
{"learn":[0.3704969981],"iteration":226,"passed_time":883.3762524,"remaining_time":3008.149089},
{"learn":[0.3700941634],"iteration":227,"passed_time":887.3701115,"remaining_time":3004.604062},
{"learn":[0.3700620765],"iteration":228,"passed_time":891.2977168,"remaining_time":3000.832051},
{"learn":[0.369987988],"iteration":229,"passed_time":896.0167357,"remaining_time":2999.708202},
{"learn":[0.3694704199],"iteration":230,"passed_time":900.1130897,"remaining_time":2996.480372},
{"learn":[0.3691680869],"iteration":231,"passed_time":904.338597,"remaining_time":2993.672597},
{"learn":[0.3690759104],"iteration":232,"passed_time":908.0370625,"remaining_time":2989.117712},
{"learn":[0.3689825167],"iteration":233,"passed_time":912.982084,"remaining_time":2988.650754},
{"learn":[0.3687456759],"iteration":234,"passed_time":917.2158909,"remaining_time":2985.830453},
{"learn":[0.368367247],"iteration":235,"passed_time":921.1020309,"remaining_time":2981.872676},
{"learn":[0.367950987],"iteration":236,"passed_time":924.2831525,"remaining_time":2975.645761},
{"learn":[0.3676844914],"iteration":237,"passed_time":928.2661955,"remaining_time":2972.011937},
{"learn":[0.3675324329],"iteration":238,"passed_time":932.8124942,"remaining_time":2970.168653},
{"learn":[0.3673052551],"iteration":239,"passed_time":936.757741,"remaining_time":2966.399513},
{"learn":[0.3672322457],"iteration":240,"passed_time":941.644553,"remaining_time":2965.594256},
{"learn":[0.3670372203],"iteration":241,"passed_time":945.5148133,"remaining_time":2961.571192},
{"learn":[0.366895344],"iteration":242,"passed_time":950.0104027,"remaining_time":2959.497427},
{"learn":[0.3667688628],"iteration":243,"passed_time":954.2641932,"remaining_time":2956.654631},
{"learn":[0.3664399047],"iteration":244,"passed_time":958.2384856,"remaining_time":2952.939007},
{"learn":[0.3663036952],"iteration":245,"passed_time":962.8266807,"remaining_time":2951.102916},
{"learn":[0.3658121874],"iteration":246,"passed_time":966.1512958,"remaining_time":2945.392412},
{"learn":[0.3657769579],"iteration":247,"passed_time":969.8393992,"remaining_time":2940.80334},
{"learn":[0.3656745536],"iteration":248,"passed_time":974.569815,"remaining_time":2939.365185},
{"learn":[0.3654030904],"iteration":249,"passed_time":978.5381028,"remaining_time":2935.614308},
{"learn":[0.3652859434],"iteration":250,"passed_time":982.936272,"remaining_time":2933.144493},
{"learn":[0.3651657042],"iteration":251,"passed_time":987.2535072,"remaining_time":2930.419141},
{"learn":[0.3651033609],"iteration":252,"passed_time":991.7948574,"remaining_time":2928.342919},
{"learn":[0.3649645546],"iteration":253,"passed_time":996.1360052,"remaining_time":2925.659291},
{"learn":[0.3648873321],"iteration":254,"passed_time":999.7825741,"remaining_time":2920.933403},
{"learn":[0.3648466024],"iteration":255,"passed_time":1004.145285,"remaining_time":2918.297235},
{"learn":[0.3646574894],"iteration":256,"passed_time":1008.701886,"remaining_time":2916.208178},
{"learn":[0.3644938091],"iteration":257,"passed_time":1012.767334,"remaining_time":2912.68745},
{"learn":[0.3643078783],"iteration":258,"passed_time":1017.17064,"remaining_time":2910.129129},
{"learn":[0.36422294],"iteration":259,"passed_time":1020.824811,"remaining_time":2905.424463},
{"learn":[0.3641716888],"iteration":260,"passed_time":1024.748239,"remaining_time":2901.490224},
{"learn":[0.364142026],"iteration":261,"passed_time":1027.995923,"remaining_time":2895.652639},
{"learn":[0.3640441816],"iteration":262,"passed_time":1030.923398,"remaining_time":2888.93743},
{"learn":[0.3639386924],"iteration":263,"passed_time":1035.222313,"remaining_time":2886.074326},
{"learn":[0.3636449094],"iteration":264,"passed_time":1039.239341,"remaining_time":2882.418551},
{"learn":[0.363448146],"iteration":265,"passed_time":1043.240821,"remaining_time":2878.717152},
{"learn":[0.3634000717],"iteration":266,"passed_time":1047.003163,"remaining_time":2874.356998},
{"learn":[0.3632172898],"iteration":267,"passed_time":1051.343279,"remaining_time":2871.579403},
{"learn":[0.3629680864],"iteration":268,"passed_time":1055.974496,"remaining_time":2869.581251},
{"learn":[0.3627138563],"iteration":269,"passed_time":1061.401312,"remaining_time":2869.714657},
{"learn":[0.3626775799],"iteration":270,"passed_time":1067.177683,"remaining_time":2870.747346},
{"learn":[0.3626057611],"iteration":271,"passed_time":1071.75579,"remaining_time":2868.522848},
{"learn":[0.3624810588],"iteration":272,"passed_time":1076.025673,"remaining_time":2865.460308},
{"learn":[0.362416392],"iteration":273,"passed_time":1079.700608,"remaining_time":2860.81256},
{"learn":[0.3623746127],"iteration":274,"passed_time":1084.21437,"remaining_time":2858.38334},
{"learn":[0.3621695342],"iteration":275,"passed_time":1088.545981,"remaining_time":2855.461196},
{"learn":[0.361959592],"iteration":276,"passed_time":1092.90256,"remaining_time":2852.594046},
{"learn":[0.3618291722],"iteration":277,"passed_time":1097.570932,"remaining_time":2850.525944},
{"learn":[0.3617632144],"iteration":278,"passed_time":1101.296075,"remaining_time":2846.001685},
{"learn":[0.3616792277],"iteration":279,"passed_time":1105.515719,"remaining_time":2842.754707},
{"learn":[0.3615569558],"iteration":280,"passed_time":1110.370561,"remaining_time":2841.126098},
{"learn":[0.3611780303],"iteration":281,"passed_time":1114.729199,"remaining_time":2838.211224},
{"learn":[0.361155688],"iteration":282,"passed_time":1118.843496,"remaining_time":2834.667091},
{"learn":[0.3609620395],"iteration":283,"passed_time":1122.524818,"remaining_time":2830.027359},
{"learn":[0.3608192846],"iteration":284,"passed_time":1126.979351,"remaining_time":2827.334161},
{"learn":[0.3606926294],"iteration":285,"passed_time":1131.568352,"remaining_time":2824.964348},
{"learn":[0.3606313427],"iteration":286,"passed_time":1136.213366,"remaining_time":2822.718223},
{"learn":[0.3604566774],"iteration":287,"passed_time":1140.558314,"remaining_time":2819.713608},
{"learn":[0.3602901433],"iteration":288,"passed_time":1144.583484,"remaining_time":2815.913},
{"learn":[0.3602151417],"iteration":289,"passed_time":1149.284347,"remaining_time":2813.765125},
{"learn":[0.3601733608],"iteration":290,"passed_time":1153.894036,"remaining_time":2811.377564},
{"learn":[0.3600604839],"iteration":291,"passed_time":1158.241747,"remaining_time":2808.339578},
{"learn":[0.3599907942],"iteration":292,"passed_time":1162.874228,"remaining_time":2805.979792},
{"learn":[0.3599405974],"iteration":293,"passed_time":1167.001615,"remaining_time":2802.391634},
{"learn":[0.3597645085],"iteration":294,"passed_time":1171.265268,"remaining_time":2799.125471},
{"learn":[0.3596741618],"iteration":295,"passed_time":1175.375648,"remaining_time":2795.488027},
{"learn":[0.3596366131],"iteration":296,"passed_time":1179.897041,"remaining_time":2792.82027},
{"learn":[0.3593959201],"iteration":297,"passed_time":1183.968203,"remaining_time":2789.079457},
{"learn":[0.3593269198],"iteration":298,"passed_time":1188.324678,"remaining_time":2786.005349},
{"learn":[0.3592205101],"iteration":299,"passed_time":1192.499178,"remaining_time":2782.498082},
{"learn":[0.3591651731],"iteration":300,"passed_time":1196.233351,"remaining_time":2777.963828},
{"learn":[0.3590772542],"iteration":301,"passed_time":1199.876998,"remaining_time":2773.225643},
{"learn":[0.3589843275],"iteration":302,"passed_time":1204.521568,"remaining_time":2770.797137},
{"learn":[0.3589552932],"iteration":303,"passed_time":1209.096272,"remaining_time":2768.194097},
{"learn":[0.3588799808],"iteration":304,"passed_time":1213.751894,"remaining_time":2765.762513},
{"learn":[0.3588587303],"iteration":305,"passed_time":1218.382639,"remaining_time":2763.259973},
{"learn":[0.3587529679],"iteration":306,"passed_time":1222.027103,"remaining_time":2758.517206},
{"learn":[0.3584968948],"iteration":307,"passed_time":1225.894854,"remaining_time":2754.283243},
{"learn":[0.3581107366],"iteration":308,"passed_time":1228.956357,"remaining_time":2748.248682},
{"learn":[0.3580402099],"iteration":309,"passed_time":1233.733713,"remaining_time":2746.052458},
{"learn":[0.3578170406],"iteration":310,"passed_time":1239.775048,"remaining_time":2746.639897},
{"learn":[0.3577465923],"iteration":311,"passed_time":1245.702507,"remaining_time":2746.933734},
{"learn":[0.3575153555],"iteration":312,"passed_time":1251.139197,"remaining_time":2746.110635},
{"learn":[0.357464648],"iteration":313,"passed_time":1256.453626,"remaining_time":2744.991042},
{"learn":[0.3573011871],"iteration":314,"passed_time":1260.708866,"remaining_time":2741.541501},
{"learn":[0.3571375886],"iteration":315,"passed_time":1264.673371,"remaining_time":2737.45755},
{"learn":[0.3568873271],"iteration":316,"passed_time":1268.992053,"remaining_time":2734.137451},
{"learn":[0.3568058878],"iteration":317,"passed_time":1273.362378,"remaining_time":2730.92183},
{"learn":[0.3567199644],"iteration":318,"passed_time":1277.535026,"remaining_time":2727.276968},
{"learn":[0.3565993863],"iteration":319,"passed_time":1281.732488,"remaining_time":2723.681538},
{"learn":[0.3564039868],"iteration":320,"passed_time":1286.400175,"remaining_time":2721.077006},
{"learn":[0.3563745414],"iteration":321,"passed_time":1290.133946,"remaining_time":2716.493215},
{"learn":[0.3563046844],"iteration":322,"passed_time":1294.453006,"remaining_time":2713.141441},
{"learn":[0.355919521],"iteration":323,"passed_time":1297.535161,"remaining_time":2707.202991},
{"learn":[0.3558321629],"iteration":324,"passed_time":1302.194933,"remaining_time":2704.558707},
{"learn":[0.355785661],"iteration":325,"passed_time":1307.127031,"remaining_time":2702.465089},
{"learn":[0.3557191524],"iteration":326,"passed_time":1311.838532,"remaining_time":2699.900098},
{"learn":[0.3556780206],"iteration":327,"passed_time":1316.355747,"remaining_time":2696.92397},
{"learn":[0.3555335469],"iteration":328,"passed_time":1320.924695,"remaining_time":2694.043984},
{"learn":[0.355414473],"iteration":329,"passed_time":1325.409135,"remaining_time":2690.982184},
{"learn":[0.3553099072],"iteration":330,"passed_time":1330.293582,"remaining_time":2688.720262},
{"learn":[0.3552425556],"iteration":331,"passed_time":1335.217289,"remaining_time":2686.521534},
{"learn":[0.3550529031],"iteration":332,"passed_time":1339.952285,"remaining_time":2683.928451},
{"learn":[0.3550218361],"iteration":333,"passed_time":1343.939614,"remaining_time":2679.831685},
{"learn":[0.3549102865],"iteration":334,"passed_time":1348.263818,"remaining_time":2676.404296},
{"learn":[0.3547402212],"iteration":335,"passed_time":1351.837747,"remaining_time":2671.488882},
{"learn":[0.354722352],"iteration":336,"passed_time":1356.397412,"remaining_time":2668.520724},
{"learn":[0.3545708234],"iteration":337,"passed_time":1360.553787,"remaining_time":2664.753275},
{"learn":[0.3545123494],"iteration":338,"passed_time":1365.624216,"remaining_time":2662.765801},
{"learn":[0.354358867],"iteration":339,"passed_time":1370.538033,"remaining_time":2660.456182},
{"learn":[0.3542975612],"iteration":340,"passed_time":1375.157391,"remaining_time":2657.56223},
{"learn":[0.3542772513],"iteration":341,"passed_time":1378.966531,"remaining_time":2653.09935},
{"learn":[0.3541558989],"iteration":342,"passed_time":1383.348913,"remaining_time":2649.738297},
{"learn":[0.3538932702],"iteration":343,"passed_time":1387.369727,"remaining_time":2645.681806},
{"learn":[0.3538289257],"iteration":344,"passed_time":1392.823247,"remaining_time":2644.345585},
{"learn":[0.3537246759],"iteration":345,"passed_time":1397.973623,"remaining_time":2642.412571},
{"learn":[0.3535714874],"iteration":346,"passed_time":1403.531886,"remaining_time":2641.228592},
{"learn":[0.3534662623],"iteration":347,"passed_time":1408.234359,"remaining_time":2638.416097},
{"learn":[0.3534182453],"iteration":348,"passed_time":1412.126322,"remaining_time":2634.080903},
{"learn":[0.3533089771],"iteration":349,"passed_time":1416.806203,"remaining_time":2631.21152},
{"learn":[0.3531710463],"iteration":350,"passed_time":1421.249183,"remaining_time":2627.893788},
{"learn":[0.3530323561],"iteration":351,"passed_time":1425.333636,"remaining_time":2623.909648},
{"learn":[0.3529929818],"iteration":352,"passed_time":1429.947415,"remaining_time":2620.895121},
{"learn":[0.3528951341],"iteration":353,"passed_time":1434.717562,"remaining_time":2618.156907},
{"learn":[0.3528100685],"iteration":354,"passed_time":1438.500075,"remaining_time":2613.612812},
{"learn":[0.3525720324],"iteration":355,"passed_time":1441.861736,"remaining_time":2608.311679},
{"learn":[0.3524543703],"iteration":356,"passed_time":1446.632146,"remaining_time":2605.55874},
{"learn":[0.3522597721],"iteration":357,"passed_time":1451.173815,"remaining_time":2602.384328},
{"learn":[0.3520858645],"iteration":358,"passed_time":1455.533012,"remaining_time":2598.876493},
{"learn":[0.3519683109],"iteration":359,"passed_time":1459.998547,"remaining_time":2595.552973},
{"learn":[0.351921402],"iteration":360,"passed_time":1464.795841,"remaining_time":2592.810366},
{"learn":[0.3518610211],"iteration":361,"passed_time":1469.162504,"remaining_time":2589.297452},
{"learn":[0.3518280663],"iteration":362,"passed_time":1473.750922,"remaining_time":2586.168973},
{"learn":[0.3517893661],"iteration":363,"passed_time":1478.4219,"remaining_time":2583.176727},
{"learn":[0.3516807946],"iteration":364,"passed_time":1482.640249,"remaining_time":2579.387831},
{"learn":[0.3516132612],"iteration":365,"passed_time":1487.591993,"remaining_time":2576.867005},
{"learn":[0.351443311],"iteration":366,"passed_time":1492.388087,"remaining_time":2574.064466},
{"learn":[0.3513406217],"iteration":367,"passed_time":1495.773518,"remaining_time":2568.828433},
{"learn":[0.3512817931],"iteration":368,"passed_time":1500.838082,"remaining_time":2566.473793},
{"learn":[0.3511346983],"iteration":369,"passed_time":1504.640994,"remaining_time":2561.956287},
{"learn":[0.3509450654],"iteration":370,"passed_time":1508.950146,"remaining_time":2558.300921},
{"learn":[0.3507993073],"iteration":371,"passed_time":1513.245466,"remaining_time":2554.618689},
{"learn":[0.3507667538],"iteration":372,"passed_time":1516.909236,"remaining_time":2549.871557},
{"learn":[0.3506993069],"iteration":373,"passed_time":1521.550374,"remaining_time":2546.766133},
{"learn":[0.3506095101],"iteration":374,"passed_time":1526.771882,"remaining_time":2544.619803},
{"learn":[0.350377318],"iteration":375,"passed_time":1532.353053,"remaining_time":2543.054003},
{"learn":[0.3500623595],"iteration":376,"passed_time":1538.476771,"remaining_time":2542.36347},
{"learn":[0.3499843847],"iteration":377,"passed_time":1542.868419,"remaining_time":2538.794065},
{"learn":[0.3499443029],"iteration":378,"passed_time":1546.409508,"remaining_time":2533.826661},
{"learn":[0.3498613884],"iteration":379,"passed_time":1551.041088,"remaining_time":2530.645985},
{"learn":[0.3496812932],"iteration":380,"passed_time":1555.236751,"remaining_time":2526.749473},
{"learn":[0.3495860899],"iteration":381,"passed_time":1560.118074,"remaining_time":2523.960653},
{"learn":[0.3495114955],"iteration":382,"passed_time":1564.046766,"remaining_time":2519.626252},
{"learn":[0.3494506307],"iteration":383,"passed_time":1568.192469,"remaining_time":2515.642086},
{"learn":[0.3492313806],"iteration":384,"passed_time":1571.39147,"remaining_time":2510.144815},
{"learn":[0.349190963],"iteration":385,"passed_time":1575.899583,"remaining_time":2506.741824},
{"learn":[0.3489525396],"iteration":386,"passed_time":1579.374718,"remaining_time":2501.696905},
{"learn":[0.3488752447],"iteration":387,"passed_time":1584.238465,"remaining_time":2498.850362},
{"learn":[0.3487881478],"iteration":388,"passed_time":1587.912653,"remaining_time":2494.125015},
{"learn":[0.3487616693],"iteration":389,"passed_time":1591.75014,"remaining_time":2489.660476},
{"learn":[0.3486367184],"iteration":390,"passed_time":1595.778318,"remaining_time":2485.496153},
{"learn":[0.3485808515],"iteration":391,"passed_time":1600.002615,"remaining_time":2481.636709},
{"learn":[0.3484431314],"iteration":392,"passed_time":1604.357787,"remaining_time":2477.977549},
{"learn":[0.3483882529],"iteration":393,"passed_time":1608.094897,"remaining_time":2473.364233},
{"learn":[0.3483008216],"iteration":394,"passed_time":1611.933754,"remaining_time":2468.911193},
{"learn":[0.3480108152],"iteration":395,"passed_time":1615.998359,"remaining_time":2464.805579},
{"learn":[0.3479149477],"iteration":396,"passed_time":1620.368125,"remaining_time":2461.163676},
{"learn":[0.3477216747],"iteration":397,"passed_time":1625.050609,"remaining_time":2457.991122},
{"learn":[0.3476929839],"iteration":398,"passed_time":1628.748852,"remaining_time":2453.328471},
{"learn":[0.3476494031],"iteration":399,"passed_time":1633.130645,"remaining_time":2449.695967},
{"learn":[0.3475235882],"iteration":400,"passed_time":1637.350046,"remaining_time":2445.817151},
{"learn":[0.3473910988],"iteration":401,"passed_time":1641.73678,"remaining_time":2442.185559},
{"learn":[0.3472786497],"iteration":402,"passed_time":1647.452585,"remaining_time":2440.51909},
{"learn":[0.3472404326],"iteration":403,"passed_time":1652.568122,"remaining_time":2437.947031},
{"learn":[0.3471192782],"iteration":404,"passed_time":1657.864091,"remaining_time":2435.627491},
{"learn":[0.3471095089],"iteration":405,"passed_time":1662.636383,"remaining_time":2432.527122},
{"learn":[0.3470246593],"iteration":406,"passed_time":1667.237758,"remaining_time":2429.16951},
{"learn":[0.3468964735],"iteration":407,"passed_time":1671.822898,"remaining_time":2425.782244},
{"learn":[0.3468781072],"iteration":408,"passed_time":1675.480313,"remaining_time":2421.048569},
{"learn":[0.3468029412],"iteration":409,"passed_time":1680.173542,"remaining_time":2417.810707},
{"learn":[0.3466000881],"iteration":410,"passed_time":1684.123616,"remaining_time":2413.500754},
{"learn":[0.346561922],"iteration":411,"passed_time":1687.424113,"remaining_time":2408.265482},
{"learn":[0.3465277906],"iteration":412,"passed_time":1691.835475,"remaining_time":2404.618459},
{"learn":[0.3463719666],"iteration":413,"passed_time":1696.401876,"remaining_time":2401.187196},
{"learn":[0.3462904382],"iteration":414,"passed_time":1701.179048,"remaining_time":2398.047574},
{"learn":[0.346145556],"iteration":415,"passed_time":1705.668281,"remaining_time":2394.495855},
{"learn":[0.3460696066],"iteration":416,"passed_time":1709.171371,"remaining_time":2389.560933},
{"learn":[0.3458691273],"iteration":417,"passed_time":1712.95873,"remaining_time":2385.028662},
{"learn":[0.3457400799],"iteration":418,"passed_time":1716.831235,"remaining_time":2380.618013},
{"learn":[0.3456628435],"iteration":419,"passed_time":1721.15375,"remaining_time":2376.831368},
{"learn":[0.3455137568],"iteration":420,"passed_time":1725.26147,"remaining_time":2372.746773},
{"learn":[0.3454191092],"iteration":421,"passed_time":1729.035765,"remaining_time":2368.205384},
{"learn":[0.3453396747],"iteration":422,"passed_time":1733.064399,"remaining_time":2364.014559},
{"learn":[0.3452955715],"iteration":423,"passed_time":1736.862421,"remaining_time":2359.511213},
{"learn":[0.3452294934],"iteration":424,"passed_time":1740.678325,"remaining_time":2355.035381},
{"learn":[0.3451114408],"iteration":425,"passed_time":1745.171263,"remaining_time":2351.474894},
{"learn":[0.3449854536],"iteration":426,"passed_time":1751.095561,"remaining_time":2349.830812},
{"learn":[0.3447770933],"iteration":427,"passed_time":1757.140827,"remaining_time":2348.328395},
{"learn":[0.3446625217],"iteration":428,"passed_time":1763.412795,"remaining_time":2347.106541},
{"learn":[0.3444767673],"iteration":429,"passed_time":1767.591276,"remaining_time":2343.08611},
{"learn":[0.3443146595],"iteration":430,"passed_time":1771.648712,"remaining_time":2338.905144},
{"learn":[0.3442017747],"iteration":431,"passed_time":1776.564108,"remaining_time":2335.852809},
{"learn":[0.3440572099],"iteration":432,"passed_time":1780.591282,"remaining_time":2331.628768},
{"learn":[0.3438665517],"iteration":433,"passed_time":1784.770013,"remaining_time":2327.603289},
{"learn":[0.3436258175],"iteration":434,"passed_time":1788.909984,"remaining_time":2323.526761},
{"learn":[0.3435179098],"iteration":435,"passed_time":1792.772723,"remaining_time":2319.09132},
{"learn":[0.3434105769],"iteration":436,"passed_time":1797.009713,"remaining_time":2315.14066},
{"learn":[0.343316112],"iteration":437,"passed_time":1801.272891,"remaining_time":2311.222294},
{"learn":[0.3432337982],"iteration":438,"passed_time":1805.821265,"remaining_time":2307.66681},
{"learn":[0.3431247624],"iteration":439,"passed_time":1809.419658,"remaining_time":2302.897747},
{"learn":[0.3430410755],"iteration":440,"passed_time":1813.868116,"remaining_time":2299.211512},
{"learn":[0.3429285378],"iteration":441,"passed_time":1818.495707,"remaining_time":2295.747975},
{"learn":[0.3428923858],"iteration":442,"passed_time":1823.321881,"remaining_time":2292.528866},
{"learn":[0.342853912],"iteration":443,"passed_time":1826.575534,"remaining_time":2287.333326},
{"learn":[0.3428333668],"iteration":444,"passed_time":1830.171747,"remaining_time":2282.573752},
{"learn":[0.3427950862],"iteration":445,"passed_time":1834.555742,"remaining_time":2278.79794},
{"learn":[0.3426412117],"iteration":446,"passed_time":1839.014678,"remaining_time":2275.112118},
{"learn":[0.3426361176],"iteration":447,"passed_time":1843.868397,"remaining_time":2271.909275},
{"learn":[0.3425643367],"iteration":448,"passed_time":1847.791474,"remaining_time":2267.55702},
{"learn":[0.3425184668],"iteration":449,"passed_time":1851.456208,"remaining_time":2262.890921},
{"learn":[0.3423477652],"iteration":450,"passed_time":1856.250216,"remaining_time":2259.603921},
{"learn":[0.3422682373],"iteration":451,"passed_time":1861.792112,"remaining_time":2257.216985},
{"learn":[0.342200559],"iteration":452,"passed_time":1867.311519,"remaining_time":2254.788964},
{"learn":[0.3421278382],"iteration":453,"passed_time":1873.382775,"remaining_time":2253.011002},
{"learn":[0.3421036665],"iteration":454,"passed_time":1878.990369,"remaining_time":2250.658794},
{"learn":[0.3420619478],"iteration":455,"passed_time":1883.470545,"remaining_time":2246.947316},
{"learn":[0.3420026024],"iteration":456,"passed_time":1887.644734,"remaining_time":2242.868907},
{"learn":[0.341949284],"iteration":457,"passed_time":1891.795856,"remaining_time":2238.762781},
{"learn":[0.3419042671],"iteration":458,"passed_time":1896.347628,"remaining_time":2235.128686},
{"learn":[0.3418169189],"iteration":459,"passed_time":1900.241235,"remaining_time":2230.717972},
{"learn":[0.3416700739],"iteration":460,"passed_time":1904.898696,"remaining_time":2227.202597},
{"learn":[0.3415399059],"iteration":461,"passed_time":1908.976674,"remaining_time":2223.007469},
{"learn":[0.3414867024],"iteration":462,"passed_time":1913.640835,"remaining_time":2219.492718},
{"learn":[0.3413205045],"iteration":463,"passed_time":1918.01626,"remaining_time":2215.639472},
{"learn":[0.3412564502],"iteration":464,"passed_time":1921.966986,"remaining_time":2211.295349},
{"learn":[0.3411319841],"iteration":465,"passed_time":1926.033955,"remaining_time":2207.08612},
{"learn":[0.3410035882],"iteration":466,"passed_time":1930.176875,"remaining_time":2202.964184},
{"learn":[0.340933834],"iteration":467,"passed_time":1934.70157,"remaining_time":2199.276143},
{"learn":[0.3409068516],"iteration":468,"passed_time":1938.597234,"remaining_time":2194.872348},
{"learn":[0.3408046607],"iteration":469,"passed_time":1943.292286,"remaining_time":2191.372152},
{"learn":[0.3406264152],"iteration":470,"passed_time":1947.953573,"remaining_time":2187.82896},
{"learn":[0.3404198874],"iteration":471,"passed_time":1952.110269,"remaining_time":2183.716572},
{"learn":[0.3403781486],"iteration":472,"passed_time":1955.962076,"remaining_time":2179.264301},
{"learn":[0.3403508412],"iteration":473,"passed_time":1959.767082,"remaining_time":2174.762627},
{"learn":[0.3402890243],"iteration":474,"passed_time":1964.574324,"remaining_time":2171.371622},
{"learn":[0.3402250123],"iteration":475,"passed_time":1969.743139,"remaining_time":2168.3727},
{"learn":[0.3399778466],"iteration":476,"passed_time":1974.718999,"remaining_time":2165.153117},
{"learn":[0.3398713388],"iteration":477,"passed_time":1980.641425,"remaining_time":2162.959883},
{"learn":[0.3397963729],"iteration":478,"passed_time":1985.926838,"remaining_time":2160.058209},
{"learn":[0.3397548086],"iteration":479,"passed_time":1992.29064,"remaining_time":2158.31486},
{"learn":[0.3396762877],"iteration":480,"passed_time":1996.938744,"remaining_time":2154.701057},
{"learn":[0.3396493944],"iteration":481,"passed_time":2000.866647,"remaining_time":2150.30897},
{"learn":[0.3396283926],"iteration":482,"passed_time":2005.487019,"remaining_time":2146.660018},
{"learn":[0.3395736557],"iteration":483,"passed_time":2009.292422,"remaining_time":2142.138202},
{"learn":[0.3394617507],"iteration":484,"passed_time":2013.338379,"remaining_time":2137.874774},
{"learn":[0.3393575984],"iteration":485,"passed_time":2018.199113,"remaining_time":2134.473959},
{"learn":[0.3391941845],"iteration":486,"passed_time":2022.206168,"remaining_time":2130.167893},
{"learn":[0.3390093539],"iteration":487,"passed_time":2026.398909,"remaining_time":2126.057872},
{"learn":[0.3389238118],"iteration":488,"passed_time":2031.301888,"remaining_time":2122.689703},
{"learn":[0.3388841501],"iteration":489,"passed_time":2036.124363,"remaining_time":2119.23148},
{"learn":[0.3387741821],"iteration":490,"passed_time":2040.967741,"remaining_time":2115.789368},
{"learn":[0.3387557886],"iteration":491,"passed_time":2044.70843,"remaining_time":2111.203013},
{"learn":[0.3387274775],"iteration":492,"passed_time":2048.860401,"remaining_time":2107.043049},
{"learn":[0.3385309366],"iteration":493,"passed_time":2053.424607,"remaining_time":2103.305366},
{"learn":[0.3384728523],"iteration":494,"passed_time":2057.007465,"remaining_time":2098.563172},
{"learn":[0.338386076],"iteration":495,"passed_time":2060.146957,"remaining_time":2093.375134},
{"learn":[0.338314094],"iteration":496,"passed_time":2063.73332,"remaining_time":2088.647606},
{"learn":[0.3382643964],"iteration":497,"passed_time":2067.880852,"remaining_time":2084.490337},
{"learn":[0.3381694859],"iteration":498,"passed_time":2072.344785,"remaining_time":2080.650776},
{"learn":[0.3381490049],"iteration":499,"passed_time":2076.785061,"remaining_time":2076.785061},
{"learn":[0.3379948224],"iteration":500,"passed_time":2080.905466,"remaining_time":2072.598458},
{"learn":[0.3379075774],"iteration":501,"passed_time":2085.333802,"remaining_time":2068.717596},
{"learn":[0.3378041082],"iteration":502,"passed_time":2089.772476,"remaining_time":2064.844773},
{"learn":[0.3377767797],"iteration":503,"passed_time":2093.505967,"remaining_time":2060.275714},
{"learn":[0.3377012834],"iteration":504,"passed_time":2097.595495,"remaining_time":2056.058951},
{"learn":[0.3376895558],"iteration":505,"passed_time":2101.349177,"remaining_time":2051.51481},
{"learn":[0.3376568966],"iteration":506,"passed_time":2105.867525,"remaining_time":2047.717337},
{"learn":[0.3376109522],"iteration":507,"passed_time":2111.618274,"remaining_time":2045.110611},
{"learn":[0.337558017],"iteration":508,"passed_time":2117.387889,"remaining_time":2042.509732},
{"learn":[0.3375292227],"iteration":509,"passed_time":2123.000263,"remaining_time":2039.745351},
{"learn":[0.337453283],"iteration":510,"passed_time":2129.213213,"remaining_time":2037.544542},
{"learn":[0.3374157871],"iteration":511,"passed_time":2133.154664,"remaining_time":2033.163039},
{"learn":[0.3373102743],"iteration":512,"passed_time":2137.5791,"remaining_time":2029.241758},
{"learn":[0.3372180124],"iteration":513,"passed_time":2142.142946,"remaining_time":2025.450334},
{"learn":[0.3371468975],"iteration":514,"passed_time":2146.489812,"remaining_time":2021.45157},
{"learn":[0.3371347114],"iteration":515,"passed_time":2151.345214,"remaining_time":2017.928456},
{"learn":[0.3370804005],"iteration":516,"passed_time":2155.753282,"remaining_time":2013.982273},
{"learn":[0.3369959965],"iteration":517,"passed_time":2159.661309,"remaining_time":2009.569017},
{"learn":[0.3369204247],"iteration":518,"passed_time":2164.035406,"remaining_time":2005.589654},
{"learn":[0.3367716987],"iteration":519,"passed_time":2168.320666,"remaining_time":2001.526769},
{"learn":[0.336760513],"iteration":520,"passed_time":2172.820427,"remaining_time":1997.660239},
{"learn":[0.3366653233],"iteration":521,"passed_time":2176.699964,"remaining_time":1993.223338},
{"learn":[0.3365399539],"iteration":522,"passed_time":2180.428299,"remaining_time":1988.650667},
{"learn":[0.3364840693],"iteration":523,"passed_time":2185.009687,"remaining_time":1984.856128},
{"learn":[0.336380688],"iteration":524,"passed_time":2189.820782,"remaining_time":1981.266422},
{"learn":[0.3362921348],"iteration":525,"passed_time":2193.754527,"remaining_time":1976.881456},
{"learn":[0.3362028387],"iteration":526,"passed_time":2198.37724,"remaining_time":1973.116574},
{"learn":[0.3361663723],"iteration":527,"passed_time":2202.349656,"remaining_time":1968.767117},
{"learn":[0.3361302696],"iteration":528,"passed_time":2207.217391,"remaining_time":1965.216241},
{"learn":[0.3360941621],"iteration":529,"passed_time":2211.119297,"remaining_time":1960.803905},
{"learn":[0.3360371813],"iteration":530,"passed_time":2216.035249,"remaining_time":1957.289137},
{"learn":[0.3358282687],"iteration":531,"passed_time":2219.990647,"remaining_time":1952.924103},
{"learn":[0.3358188921],"iteration":532,"passed_time":2224.425778,"remaining_time":1948.980935},
{"learn":[0.3357329983],"iteration":533,"passed_time":2230.589364,"remaining_time":1946.544276},
{"learn":[0.3355283374],"iteration":534,"passed_time":2235.42873,"remaining_time":1942.942728},
{"learn":[0.3354916142],"iteration":535,"passed_time":2240.180811,"remaining_time":1939.261001},
{"learn":[0.3354319981],"iteration":536,"passed_time":2246.114797,"remaining_time":1936.594323},
{"learn":[0.3352881421],"iteration":537,"passed_time":2250.761596,"remaining_time":1932.810144},
{"learn":[0.3352511213],"iteration":538,"passed_time":2255.385758,"remaining_time":1929.003403},
{"learn":[0.3348932765],"iteration":539,"passed_time":2258.95132,"remaining_time":1924.291865},
{"learn":[0.3348510623],"iteration":540,"passed_time":2262.922456,"remaining_time":1919.928664},
{"learn":[0.3348479955],"iteration":541,"passed_time":2267.919401,"remaining_time":1916.433738},
{"learn":[0.3344737723],"iteration":542,"passed_time":2271.606904,"remaining_time":1911.831225},
{"learn":[0.3343642207],"iteration":543,"passed_time":2276.052929,"remaining_time":1907.867896},
{"learn":[0.3343341527],"iteration":544,"passed_time":2279.966257,"remaining_time":1903.458068},
{"learn":[0.3342853299],"iteration":545,"passed_time":2285.008917,"remaining_time":1899.9891},
{"learn":[0.3341331432],"iteration":546,"passed_time":2288.844109,"remaining_time":1895.514408},
{"learn":[0.3340540327],"iteration":547,"passed_time":2293.241382,"remaining_time":1891.505665},
{"learn":[0.3339583667],"iteration":548,"passed_time":2297.9483,"remaining_time":1887.749879},
{"learn":[0.3339028764],"iteration":549,"passed_time":2302.806491,"remaining_time":1884.114402},
{"learn":[0.3338012018],"iteration":550,"passed_time":2307.233816,"remaining_time":1880.123382},
{"learn":[0.3336937175],"iteration":551,"passed_time":2310.74602,"remaining_time":1875.388074},
{"learn":[0.3336207404],"iteration":552,"passed_time":2314.574046,"remaining_time":1870.912475},
{"learn":[0.3335480293],"iteration":553,"passed_time":2318.673014,"remaining_time":1866.657336},
{"learn":[0.3334604032],"iteration":554,"passed_time":2323.096884,"remaining_time":1862.663267},
{"learn":[0.3334395233],"iteration":555,"passed_time":2326.850961,"remaining_time":1858.132782},
{"learn":[0.3333528524],"iteration":556,"passed_time":2331.284426,"remaining_time":1854.145423},
{"learn":[0.3332654491],"iteration":557,"passed_time":2336.221575,"remaining_time":1850.555441},
{"learn":[0.3332241747],"iteration":558,"passed_time":2340.747046,"remaining_time":1846.635862},
{"learn":[0.333192515],"iteration":559,"passed_time":2345.71149,"remaining_time":1843.059028},
{"learn":[0.333130315],"iteration":560,"passed_time":2351.470066,"remaining_time":1840.098679},
{"learn":[0.3330685548],"iteration":561,"passed_time":2356.286075,"remaining_time":1836.393774},
{"learn":[0.3329120925],"iteration":562,"passed_time":2360.230017,"remaining_time":1832.008024},
{"learn":[0.3328236324],"iteration":563,"passed_time":2364.874746,"remaining_time":1828.165584},
{"learn":[0.3326175425],"iteration":564,"passed_time":2369.314127,"remaining_time":1824.162204},
{"learn":[0.3325401574],"iteration":565,"passed_time":2374.562314,"remaining_time":1820.777463},
{"learn":[0.332487813],"iteration":566,"passed_time":2378.22166,"remaining_time":1816.172802},
{"learn":[0.3324262971],"iteration":567,"passed_time":2382.017848,"remaining_time":1811.675547},
{"learn":[0.3321852218],"iteration":568,"passed_time":2386.488154,"remaining_time":1807.691378},
{"learn":[0.3321351693],"iteration":569,"passed_time":2390.934107,"remaining_time":1803.687133},
{"learn":[0.3319875071],"iteration":570,"passed_time":2394.56339,"remaining_time":1799.067766},
{"learn":[0.3319205724],"iteration":571,"passed_time":2399.558384,"remaining_time":1795.473756},
{"learn":[0.3318720107],"iteration":572,"passed_time":2404.295752,"remaining_time":1791.682873},
{"learn":[0.3318020899],"iteration":573,"passed_time":2409.088118,"remaining_time":1787.929509},
{"learn":[0.33171924],"iteration":574,"passed_time":2414.053938,"remaining_time":1784.300737},
{"learn":[0.3316163154],"iteration":575,"passed_time":2417.745506,"remaining_time":1779.729331},
{"learn":[0.3315737919],"iteration":576,"passed_time":2421.774091,"remaining_time":1775.408043},
{"learn":[0.3315276171],"iteration":577,"passed_time":2426.491808,"remaining_time":1771.590905},
{"learn":[0.3314658775],"iteration":578,"passed_time":2431.309011,"remaining_time":1767.842994},
{"learn":[0.331348709],"iteration":579,"passed_time":2436.395121,"remaining_time":1764.286122},
{"learn":[0.3311356748],"iteration":580,"passed_time":2442.454446,"remaining_time":1761.42584},
{"learn":[0.3311139228],"iteration":581,"passed_time":2448.973176,"remaining_time":1758.884515},
{"learn":[0.330992616],"iteration":582,"passed_time":2453.908891,"remaining_time":1755.197269},
{"learn":[0.3309373631],"iteration":583,"passed_time":2458.940346,"remaining_time":1751.573945},
{"learn":[0.3308968412],"iteration":584,"passed_time":2463.844842,"remaining_time":1747.855743},
{"learn":[0.3307721033],"iteration":585,"passed_time":2468.359296,"remaining_time":1743.857933},
{"learn":[0.3306444888],"iteration":586,"passed_time":2473.194046,"remaining_time":1740.083716},
{"learn":[0.3305514933],"iteration":587,"passed_time":2477.187126,"remaining_time":1735.71615},
{"learn":[0.3304684075],"iteration":588,"passed_time":2480.97273,"remaining_time":1731.20508},
{"learn":[0.3303958059],"iteration":589,"passed_time":2485.516863,"remaining_time":1727.223583},
{"learn":[0.330327708],"iteration":590,"passed_time":2488.790844,"remaining_time":1722.361176},
{"learn":[0.3302510663],"iteration":591,"passed_time":2493.376563,"remaining_time":1718.408172},
{"learn":[0.3301715527],"iteration":592,"passed_time":2498.191976,"remaining_time":1714.610681},
{"learn":[0.3300880351],"iteration":593,"passed_time":2501.880345,"remaining_time":1710.039428},
{"learn":[0.3300392116],"iteration":594,"passed_time":2507.979319,"remaining_time":1707.111973},
{"learn":[0.3299876865],"iteration":595,"passed_time":2513.822569,"remaining_time":1704.000533},
{"learn":[0.3299057124],"iteration":596,"passed_time":2518.611161,"remaining_time":1700.168003},
{"learn":[0.329834583],"iteration":597,"passed_time":2523.529581,"remaining_time":1696.419551},
{"learn":[0.3297778811],"iteration":598,"passed_time":2527.77556,"remaining_time":1692.217028},
{"learn":[0.3296507372],"iteration":599,"passed_time":2531.982274,"remaining_time":1687.988182},
{"learn":[0.3295175501],"iteration":600,"passed_time":2536.73535,"remaining_time":1684.122137},
{"learn":[0.3294188397],"iteration":601,"passed_time":2541.295545,"remaining_time":1680.125626},
{"learn":[0.3292928799],"iteration":602,"passed_time":2545.467104,"remaining_time":1675.871377},
{"learn":[0.32925327],"iteration":603,"passed_time":2549.364046,"remaining_time":1671.437354},
{"learn":[0.3292137122],"iteration":604,"passed_time":2553.211202,"remaining_time":1666.972603},
{"learn":[0.3290463047],"iteration":605,"passed_time":2557.98392,"remaining_time":1663.111658},
{"learn":[0.3289348994],"iteration":606,"passed_time":2562.029523,"remaining_time":1658.77694},
{"learn":[0.3287812425],"iteration":607,"passed_time":2566.691187,"remaining_time":1654.84037},
{"learn":[0.3287720049],"iteration":608,"passed_time":2571.564204,"remaining_time":1651.037116},
{"learn":[0.3287173637],"iteration":609,"passed_time":2576.090794,"remaining_time":1647.008868},
{"learn":[0.3285898842],"iteration":610,"passed_time":2580.264469,"remaining_time":1642.754302},
{"learn":[0.3285503888],"iteration":611,"passed_time":2585.096802,"remaining_time":1638.917581},
{"learn":[0.3285239359],"iteration":612,"passed_time":2589.76483,"remaining_time":1634.973881},
{"learn":[0.3284701627],"iteration":613,"passed_time":2594.71852,"remaining_time":1631.207408},
{"learn":[0.328439881],"iteration":614,"passed_time":2600.466562,"remaining_time":1627.934352},
{"learn":[0.3283701],"iteration":615,"passed_time":2605.248055,"remaining_time":1624.050735},
{"learn":[0.3283407275],"iteration":616,"passed_time":2608.363358,"remaining_time":1619.129929},
{"learn":[0.3281298939],"iteration":617,"passed_time":2612.618042,"remaining_time":1614.919243},
{"learn":[0.3280273442],"iteration":618,"passed_time":2616.623698,"remaining_time":1610.555135},
{"learn":[0.3278532306],"iteration":619,"passed_time":2620.873302,"remaining_time":1606.341701},
{"learn":[0.3277985897],"iteration":620,"passed_time":2625.498245,"remaining_time":1602.357222},
{"learn":[0.3277602867],"iteration":621,"passed_time":2629.081432,"remaining_time":1597.737591},
{"learn":[0.3277054243],"iteration":622,"passed_time":2633.551612,"remaining_time":1593.658038},
{"learn":[0.3276372874],"iteration":623,"passed_time":2638.198943,"remaining_time":1589.683979},
{"learn":[0.3275171723],"iteration":624,"passed_time":2642.300663,"remaining_time":1585.380398},
{"learn":[0.3274493342],"iteration":625,"passed_time":2646.716419,"remaining_time":1581.265081},
{"learn":[0.3273800002],"iteration":626,"passed_time":2651.45061,"remaining_time":1577.338242},
{"learn":[0.3273336505],"iteration":627,"passed_time":2656.97538,"remaining_time":1573.877136},
{"learn":[0.3272349437],"iteration":628,"passed_time":2663.305285,"remaining_time":1570.884357},
{"learn":[0.3271739656],"iteration":629,"passed_time":2668.535762,"remaining_time":1567.235289},
{"learn":[0.3271232061],"iteration":630,"passed_time":2672.885846,"remaining_time":1563.066366},
{"learn":[0.3269918261],"iteration":631,"passed_time":2677.132584,"remaining_time":1558.836694},
{"learn":[0.3269435105],"iteration":632,"passed_time":2681.794439,"remaining_time":1554.847645},
{"learn":[0.3268054991],"iteration":633,"passed_time":2685.155683,"remaining_time":1550.105647},
{"learn":[0.3266666539],"iteration":634,"passed_time":2689.889949,"remaining_time":1546.157215},
{"learn":[0.3264589957],"iteration":635,"passed_time":2694.663983,"remaining_time":1542.229072},
{"learn":[0.3263421563],"iteration":636,"passed_time":2698.944281,"remaining_time":1538.016913},
{"learn":[0.3262133266],"iteration":637,"passed_time":2703.772126,"remaining_time":1534.115219},
{"learn":[0.3260686994],"iteration":638,"passed_time":2708.028984,"remaining_time":1529.888049},
{"learn":[0.3259960605],"iteration":639,"passed_time":2712.391235,"remaining_time":1525.72007},
{"learn":[0.3259266627],"iteration":640,"passed_time":2716.788804,"remaining_time":1521.571265},
{"learn":[0.3258615934],"iteration":641,"passed_time":2720.773036,"remaining_time":1517.191194},
{"learn":[0.3258279755],"iteration":642,"passed_time":2725.526546,"remaining_time":1513.239466},
{"learn":[0.3257983427],"iteration":643,"passed_time":2729.968466,"remaining_time":1509.113003},
{"learn":[0.3257785121],"iteration":644,"passed_time":2733.598929,"remaining_time":1504.538945},
{"learn":[0.3257025365],"iteration":645,"passed_time":2738.059349,"remaining_time":1500.422615},
{"learn":[0.3256713489],"iteration":646,"passed_time":2742.838101,"remaining_time":1496.478902},
{"learn":[0.3256493715],"iteration":647,"passed_time":2746.479819,"remaining_time":1491.914963},
{"learn":[0.3255533207],"iteration":648,"passed_time":2750.840522,"remaining_time":1487.742717},
{"learn":[0.325418631],"iteration":649,"passed_time":2754.60408,"remaining_time":1483.248351},
{"learn":[0.3253895887],"iteration":650,"passed_time":2759.723351,"remaining_time":1479.483025},
{"learn":[0.3252598929],"iteration":651,"passed_time":2765.2957,"remaining_time":1475.955374},
{"learn":[0.3251342132],"iteration":652,"passed_time":2771.699757,"remaining_time":1472.863424},
{"learn":[0.3250686371],"iteration":653,"passed_time":2776.976713,"remaining_time":1469.16505},
{"learn":[0.3250100068],"iteration":654,"passed_time":2781.546783,"remaining_time":1465.089527},
{"learn":[0.3249237157],"iteration":655,"passed_time":2786.262496,"remaining_time":1461.08887},
{"learn":[0.3248083932],"iteration":656,"passed_time":2790.433531,"remaining_time":1456.801676},
{"learn":[0.324571376],"iteration":657,"passed_time":2795.039765,"remaining_time":1452.741033},
{"learn":[0.3244552465],"iteration":658,"passed_time":2798.590589,"remaining_time":1448.132612},
{"learn":[0.3244287653],"iteration":659,"passed_time":2803.249669,"remaining_time":1444.098314},
{"learn":[0.3244101233],"iteration":660,"passed_time":2807.597876,"remaining_time":1439.902693},
{"learn":[0.324372289],"iteration":661,"passed_time":2812.006474,"remaining_time":1435.737444},
{"learn":[0.3241895423],"iteration":662,"passed_time":2816.814021,"remaining_time":1431.774246},
{"learn":[0.3241347563],"iteration":663,"passed_time":2820.164481,"remaining_time":1427.071183},
{"learn":[0.3240372449],"iteration":664,"passed_time":2824.251574,"remaining_time":1422.743274},
{"learn":[0.3239094316],"iteration":665,"passed_time":2827.659232,"remaining_time":1418.075351},
{"learn":[0.3237988935],"iteration":666,"passed_time":2831.80398,"remaining_time":1413.779199},
{"learn":[0.32371042],"iteration":667,"passed_time":2836.758816,"remaining_time":1409.886118},
{"learn":[0.3236648971],"iteration":668,"passed_time":2841.856004,"remaining_time":1406.060295},
{"learn":[0.3236553247],"iteration":669,"passed_time":2846.526143,"remaining_time":1402.020339},
{"learn":[0.3235308337],"iteration":670,"passed_time":2851.798628,"remaining_time":1398.273843},
{"learn":[0.3233973035],"iteration":671,"passed_time":2857.723014,"remaining_time":1394.840995},
{"learn":[0.3232933226],"iteration":672,"passed_time":2861.872924,"remaining_time":1390.538553},
{"learn":[0.3232342891],"iteration":673,"passed_time":2866.204614,"remaining_time":1386.324487},
{"learn":[0.323151041],"iteration":674,"passed_time":2870.137704,"remaining_time":1381.918154},
{"learn":[0.3230318471],"iteration":675,"passed_time":2874.11713,"remaining_time":1377.535429},
{"learn":[0.3228938341],"iteration":676,"passed_time":2877.446855,"remaining_time":1372.84392},
{"learn":[0.3228310148],"iteration":677,"passed_time":2882.047248,"remaining_time":1368.759903},
{"learn":[0.3227358758],"iteration":678,"passed_time":2886.738459,"remaining_time":1364.717298},
{"learn":[0.3227113422],"iteration":679,"passed_time":2891.654047,"remaining_time":1360.778375},
{"learn":[0.3225877054],"iteration":680,"passed_time":2895.416201,"remaining_time":1356.296282},
{"learn":[0.3225411023],"iteration":681,"passed_time":2899.509048,"remaining_time":1351.970495},
{"learn":[0.3224625024],"iteration":682,"passed_time":2904.485293,"remaining_time":1348.055399},
{"learn":[0.322303364],"iteration":683,"passed_time":2909.232095,"remaining_time":1344.031202},
{"learn":[0.3222833745],"iteration":684,"passed_time":2913.213445,"remaining_time":1339.652898},
{"learn":[0.3222004073],"iteration":685,"passed_time":2918.066659,"remaining_time":1335.674827},
{"learn":[0.3221333653],"iteration":686,"passed_time":2923.37456,"remaining_time":1331.901364},
{"learn":[0.322009736],"iteration":687,"passed_time":2929.02529,"remaining_time":1328.278911},
{"learn":[0.3218782935],"iteration":688,"passed_time":2934.060921,"remaining_time":1324.372926},
{"learn":[0.3217938392],"iteration":689,"passed_time":2939.021365,"remaining_time":1320.429889},
{"learn":[0.3217092658],"iteration":690,"passed_time":2942.891294,"remaining_time":1315.996252},
{"learn":[0.3215751837],"iteration":691,"passed_time":2947.122818,"remaining_time":1311.725185},
{"learn":[0.3215313434],"iteration":692,"passed_time":2952.020608,"remaining_time":1307.749389},
{"learn":[0.3214557463],"iteration":693,"passed_time":2956.798461,"remaining_time":1303.718054},
{"learn":[0.3213946185],"iteration":694,"passed_time":2960.770086,"remaining_time":1299.330757},
{"learn":[0.32137555],"iteration":695,"passed_time":2965.783545,"remaining_time":1295.399709},
{"learn":[0.32125216],"iteration":696,"passed_time":2969.473101,"remaining_time":1290.890028},
{"learn":[0.3212243191],"iteration":697,"passed_time":2973.875237,"remaining_time":1286.691005},
{"learn":[0.3211867218],"iteration":698,"passed_time":2978.167178,"remaining_time":1282.443949},
{"learn":[0.3211679031],"iteration":699,"passed_time":2982.246876,"remaining_time":1278.105804},
{"learn":[0.3211389008],"iteration":700,"passed_time":2985.681261,"remaining_time":1273.493148},
{"learn":[0.3210437611],"iteration":701,"passed_time":2989.706829,"remaining_time":1269.134808},
{"learn":[0.3209090071],"iteration":702,"passed_time":2993.877612,"remaining_time":1264.838763},
{"learn":[0.3208928509],"iteration":703,"passed_time":2998.589589,"remaining_time":1260.770622},
{"learn":[0.3208216745],"iteration":704,"passed_time":3002.229606,"remaining_time":1256.252105},
{"learn":[0.3207301177],"iteration":705,"passed_time":3006.857027,"remaining_time":1252.147261},
{"learn":[0.3206420655],"iteration":706,"passed_time":3010.861814,"remaining_time":1247.782902},
{"learn":[0.3205742274],"iteration":707,"passed_time":3016.021308,"remaining_time":1243.895794},
{"learn":[0.3204420431],"iteration":708,"passed_time":3020.397919,"remaining_time":1239.683772},
{"learn":[0.3204021144],"iteration":709,"passed_time":3024.398828,"remaining_time":1235.317831},
{"learn":[0.320357727],"iteration":710,"passed_time":3029.247423,"remaining_time":1231.297476},
{"learn":[0.3202020566],"iteration":711,"passed_time":3034.045929,"remaining_time":1227.254533},
{"learn":[0.3201447937],"iteration":712,"passed_time":3039.117938,"remaining_time":1223.319563},
{"learn":[0.320113557],"iteration":713,"passed_time":3042.816368,"remaining_time":1218.831206},
{"learn":[0.3200644649],"iteration":714,"passed_time":3047.329075,"remaining_time":1214.669631},
{"learn":[0.3199044562],"iteration":715,"passed_time":3051.044923,"remaining_time":1210.191003},
{"learn":[0.3198643788],"iteration":716,"passed_time":3056.429426,"remaining_time":1206.373121},
{"learn":[0.3198154314],"iteration":717,"passed_time":3062.596754,"remaining_time":1202.858335},
{"learn":[0.3197720886],"iteration":718,"passed_time":3068.336578,"remaining_time":1199.169094},
{"learn":[0.3195828522],"iteration":719,"passed_time":3072.977742,"remaining_time":1195.0469},
{"learn":[0.31941376],"iteration":720,"passed_time":3077.193633,"remaining_time":1190.758701},
{"learn":[0.3193219727],"iteration":721,"passed_time":3082.684545,"remaining_time":1186.961639},
{"learn":[0.319252748],"iteration":722,"passed_time":3087.745699,"remaining_time":1182.99524},
{"learn":[0.3191090682],"iteration":723,"passed_time":3091.80205,"remaining_time":1178.64277},
{"learn":[0.3190602247],"iteration":724,"passed_time":3097.567939,"remaining_time":1174.939563},
{"learn":[0.3188652918],"iteration":725,"passed_time":3102.51645,"remaining_time":1170.922186},
{"learn":[0.3188132592],"iteration":726,"passed_time":3106.866179,"remaining_time":1166.677396},
{"learn":[0.3187650705],"iteration":727,"passed_time":3112.411456,"remaining_time":1162.879006},
{"learn":[0.3187253355],"iteration":728,"passed_time":3117.292877,"remaining_time":1158.829039},
{"learn":[0.318705456],"iteration":729,"passed_time":3122.415971,"remaining_time":1154.866181},
{"learn":[0.3186936076],"iteration":730,"passed_time":3126.147033,"remaining_time":1150.387896},
{"learn":[0.3185511791],"iteration":731,"passed_time":3130.202722,"remaining_time":1146.030505},
{"learn":[0.3185293157],"iteration":732,"passed_time":3135.185938,"remaining_time":1142.011795},
{"learn":[0.3185101907],"iteration":733,"passed_time":3139.973948,"remaining_time":1137.919714},
{"learn":[0.3184207943],"iteration":734,"passed_time":3143.912051,"remaining_time":1133.519311},
{"learn":[0.3183992526],"iteration":735,"passed_time":3148.670823,"remaining_time":1129.414534},
{"learn":[0.3182610019],"iteration":736,"passed_time":3152.80368,"remaining_time":1125.084624},
{"learn":[0.318108174],"iteration":737,"passed_time":3156.801688,"remaining_time":1120.707374},
{"learn":[0.3180685126],"iteration":738,"passed_time":3161.911462,"remaining_time":1116.723805},
{"learn":[0.3179908706],"iteration":739,"passed_time":3165.971439,"remaining_time":1112.368343},
{"learn":[0.3178799534],"iteration":740,"passed_time":3170.338303,"remaining_time":1108.120945},
{"learn":[0.3178511457],"iteration":741,"passed_time":3174.366688,"remaining_time":1103.755533},
{"learn":[0.3177840102],"iteration":742,"passed_time":3178.442387,"remaining_time":1099.407394},
{"learn":[0.3177292889],"iteration":743,"passed_time":3184.199673,"remaining_time":1095.638597},
{"learn":[0.3176566394],"iteration":744,"passed_time":3189.068044,"remaining_time":1091.560203},
{"learn":[0.3175473067],"iteration":745,"passed_time":3194.579789,"remaining_time":1087.698749},
{"learn":[0.3175165094],"iteration":746,"passed_time":3199.008188,"remaining_time":1083.465959},
{"learn":[0.317372281],"iteration":747,"passed_time":3204.071286,"remaining_time":1079.446476},
{"learn":[0.3172836768],"iteration":748,"passed_time":3210.152019,"remaining_time":1075.765229},
{"learn":[0.3172003457],"iteration":749,"passed_time":3215.040848,"remaining_time":1071.680283},
{"learn":[0.3171094811],"iteration":750,"passed_time":3221.185535,"remaining_time":1068.009585},
{"learn":[0.317067365],"iteration":751,"passed_time":3225.89109,"remaining_time":1063.8577},
{"learn":[0.3170347831],"iteration":752,"passed_time":3231.443489,"remaining_time":1059.982127},
{"learn":[0.3170008233],"iteration":753,"passed_time":3236.229968,"remaining_time":1055.852218},
{"learn":[0.3167278544],"iteration":754,"passed_time":3240.65384,"remaining_time":1051.602902},
{"learn":[0.3167012939],"iteration":755,"passed_time":3244.6892,"remaining_time":1047.227731},
{"learn":[0.3166651348],"iteration":756,"passed_time":3249.591455,"remaining_time":1043.131735},
{"learn":[0.3165802599],"iteration":757,"passed_time":3253.422419,"remaining_time":1038.69159},
{"learn":[0.3165366889],"iteration":758,"passed_time":3257.328105,"remaining_time":1034.276776},
{"learn":[0.316474911],"iteration":759,"passed_time":3261.66244,"remaining_time":1029.998665},
{"learn":[0.316400325],"iteration":760,"passed_time":3266.566763,"remaining_time":1025.899417},
{"learn":[0.3163587044],"iteration":761,"passed_time":3271.51772,"remaining_time":1021.812621},
{"learn":[0.3162299513],"iteration":762,"passed_time":3277.156616,"remaining_time":1017.937245},
{"learn":[0.3161468768],"iteration":763,"passed_time":3282.130316,"remaining_time":1013.851773},
{"learn":[0.3161128715],"iteration":764,"passed_time":3287.327652,"remaining_time":1009.832677},
{"learn":[0.3160777841],"iteration":765,"passed_time":3291.961674,"remaining_time":1005.638423},
{"learn":[0.3159767491],"iteration":766,"passed_time":3298.820531,"remaining_time":1002.118884},
{"learn":[0.3158834644],"iteration":767,"passed_time":3304.833727,"remaining_time":998.3351882},
{"learn":[0.3158339637],"iteration":768,"passed_time":3311.086263,"remaining_time":994.6175899},
{"learn":[0.3157998659],"iteration":769,"passed_time":3316.295516,"remaining_time":990.5817776},
{"learn":[0.3157307656],"iteration":770,"passed_time":3321.458029,"remaining_time":986.5290386},
{"learn":[0.3156972915],"iteration":771,"passed_time":3326.180855,"remaining_time":982.3435687},
{"learn":[0.3156385967],"iteration":772,"passed_time":3330.966311,"remaining_time":978.1751004},
{"learn":[0.315616677],"iteration":773,"passed_time":3334.557476,"remaining_time":973.6563172},
{"learn":[0.3155353731],"iteration":774,"passed_time":3338.526626,"remaining_time":969.2496656},
{"learn":[0.3154759379],"iteration":775,"passed_time":3342.025405,"remaining_time":964.7083644},
{"learn":[0.3154397375],"iteration":776,"passed_time":3346.052459,"remaining_time":960.3213621},
{"learn":[0.3153550604],"iteration":777,"passed_time":3350.859228,"remaining_time":956.1577745},
{"learn":[0.315272597],"iteration":778,"passed_time":3356.003059,"remaining_time":952.0881592},
{"learn":[0.3152509694],"iteration":779,"passed_time":3360.946095,"remaining_time":947.9591549},
{"learn":[0.3151135341],"iteration":780,"passed_time":3364.817291,"remaining_time":943.5275119},
{"learn":[0.3150912725],"iteration":781,"passed_time":3369.677913,"remaining_time":939.3731268},
{"learn":[0.3150390629],"iteration":782,"passed_time":3375.334702,"remaining_time":935.4375867},
{"learn":[0.314990277],"iteration":783,"passed_time":3380.860864,"remaining_time":931.4616667},
{"learn":[0.3149272708],"iteration":784,"passed_time":3386.387451,"remaining_time":927.4819133},
{"learn":[0.3148440222],"iteration":785,"passed_time":3391.061186,"remaining_time":923.2660227},
{"learn":[0.3148037339],"iteration":786,"passed_time":3395.120664,"remaining_time":918.8827209},
{"learn":[0.3147162663],"iteration":787,"passed_time":3399.316694,"remaining_time":914.5369787},
{"learn":[0.3146732232],"iteration":788,"passed_time":3406.778593,"remaining_time":911.0649976},
{"learn":[0.3146058134],"iteration":789,"passed_time":3412.511442,"remaining_time":907.1232948},
{"learn":[0.314530608],"iteration":790,"passed_time":3419.207916,"remaining_time":903.4316745},
{"learn":[0.3144576498],"iteration":791,"passed_time":3425.282611,"remaining_time":899.5691705},
{"learn":[0.3144043669],"iteration":792,"passed_time":3429.93947,"remaining_time":895.330984},
{"learn":[0.3143662737],"iteration":793,"passed_time":3434.076721,"remaining_time":890.9569326},
{"learn":[0.3142878528],"iteration":794,"passed_time":3439.629804,"remaining_time":886.9485657},
{"learn":[0.3142187661],"iteration":795,"passed_time":3444.546678,"remaining_time":882.7732693},
{"learn":[0.3141111471],"iteration":796,"passed_time":3448.738597,"remaining_time":878.411462},
{"learn":[0.3140632096],"iteration":797,"passed_time":3453.661344,"remaining_time":874.2350772},
{"learn":[0.3140313958],"iteration":798,"passed_time":3458.199889,"remaining_time":869.9601724},
{"learn":[0.3139488328],"iteration":799,"passed_time":3463.359842,"remaining_time":865.8399604},
{"learn":[0.3138752271],"iteration":800,"passed_time":3468.593675,"remaining_time":861.7355072},
{"learn":[0.3138154447],"iteration":801,"passed_time":3473.933355,"remaining_time":857.6543694},
{"learn":[0.3136344106],"iteration":802,"passed_time":3480.131816,"remaining_time":853.7807817},
{"learn":[0.3135473512],"iteration":803,"passed_time":3485.95591,"remaining_time":849.8101472},
{"learn":[0.3135062672],"iteration":804,"passed_time":3490.370353,"remaining_time":845.4934396},
{"learn":[0.3134211425],"iteration":805,"passed_time":3494.862767,"remaining_time":841.1952566},
{"learn":[0.3133562251],"iteration":806,"passed_time":3499.299053,"remaining_time":836.8831689},
{"learn":[0.3132874777],"iteration":807,"passed_time":3503.895563,"remaining_time":832.6088466},
{"learn":[0.313217585],"iteration":808,"passed_time":3507.349144,"remaining_time":828.0638895},
{"learn":[0.313167346],"iteration":809,"passed_time":3512.015728,"remaining_time":823.8061583},
{"learn":[0.3130598131],"iteration":810,"passed_time":3516.340922,"remaining_time":819.4678597},
{"learn":[0.3129875428],"iteration":811,"passed_time":3520.475271,"remaining_time":815.0854076},
{"learn":[0.312907072],"iteration":812,"passed_time":3525.010385,"remaining_time":810.7957466},
{"learn":[0.3128191587],"iteration":813,"passed_time":3529.713519,"remaining_time":806.5438753},
{"learn":[0.312778003],"iteration":814,"passed_time":3534.291024,"remaining_time":802.2623798},
{"learn":[0.3124022857],"iteration":815,"passed_time":3538.106082,"remaining_time":797.8082341},
{"learn":[0.3123443666],"iteration":816,"passed_time":3542.959087,"remaining_time":793.5881432},
{"learn":[0.3122008615],"iteration":817,"passed_time":3547.984265,"remaining_time":789.404812},
{"learn":[0.3121439559],"iteration":818,"passed_time":3554.253676,"remaining_time":785.4944022},
{"learn":[0.3119798916],"iteration":819,"passed_time":3560.248664,"remaining_time":781.5179993},
{"learn":[0.3118494243],"iteration":820,"passed_time":3564.827734,"remaining_time":777.2279712},
{"learn":[0.3116721016],"iteration":821,"passed_time":3569.39286,"remaining_time":772.9342202},
{"learn":[0.3116545626],"iteration":822,"passed_time":3573.426374,"remaining_time":768.5254778},
{"learn":[0.3116375504],"iteration":823,"passed_time":3578.449732,"remaining_time":764.3290689},
{"learn":[0.3115995929],"iteration":824,"passed_time":3581.822004,"remaining_time":759.7804252},
{"learn":[0.3114343783],"iteration":825,"passed_time":3585.977409,"remaining_time":755.3995994},
{"learn":[0.3113771138],"iteration":826,"passed_time":3589.466926,"remaining_time":750.8800221},
{"learn":[0.3113160629],"iteration":827,"passed_time":3593.878817,"remaining_time":746.5545368},
{"learn":[0.3112470782],"iteration":828,"passed_time":3598.375272,"remaining_time":742.2462864},
{"learn":[0.3111469351],"iteration":829,"passed_time":3602.631172,"remaining_time":737.8883123},
{"learn":[0.3110459636],"iteration":830,"passed_time":3607.246663,"remaining_time":733.6037137},
{"learn":[0.310944663],"iteration":831,"passed_time":3611.891516,"remaining_time":729.3242484},
{"learn":[0.3109188208],"iteration":832,"passed_time":3616.581064,"remaining_time":725.0528663},
{"learn":[0.3108455034],"iteration":833,"passed_time":3621.596299,"remaining_time":720.8453064},
{"learn":[0.3107758433],"iteration":834,"passed_time":3625.946421,"remaining_time":716.5043826},
{"learn":[0.310676245],"iteration":835,"passed_time":3632.260922,"remaining_time":712.5487932},
{"learn":[0.3106550195],"iteration":836,"passed_time":3637.252108,"remaining_time":708.3298609},
{"learn":[0.3105896222],"iteration":837,"passed_time":3643.243009,"remaining_time":704.3023477},
{"learn":[0.3105277859],"iteration":838,"passed_time":3648.693743,"remaining_time":700.1664989},
{"learn":[0.3103892632],"iteration":839,"passed_time":3653.50474,"remaining_time":695.9056647},
{"learn":[0.3103109939],"iteration":840,"passed_time":3657.866436,"remaining_time":691.558577},
{"learn":[0.3101146477],"iteration":841,"passed_time":3662.612276,"remaining_time":687.2835388},
{"learn":[0.310088906],"iteration":842,"passed_time":3666.19572,"remaining_time":682.7908991},
{"learn":[0.3100153132],"iteration":843,"passed_time":3670.461783,"remaining_time":678.4265855},
{"learn":[0.3099840706],"iteration":844,"passed_time":3674.279795,"remaining_time":673.9803174},
{"learn":[0.3099015675],"iteration":845,"passed_time":3678.361807,"remaining_time":669.5835914},
{"learn":[0.3097930897],"iteration":846,"passed_time":3682.570783,"remaining_time":665.2105428},
{"learn":[0.3097454765],"iteration":847,"passed_time":3686.649409,"remaining_time":660.8145167},
{"learn":[0.3096572036],"iteration":848,"passed_time":3690.618066,"remaining_time":656.3996796},
{"learn":[0.3096410895],"iteration":849,"passed_time":3695.168033,"remaining_time":652.0884763},
{"learn":[0.30956851],"iteration":850,"passed_time":3699.887906,"remaining_time":647.8064606},
{"learn":[0.3093732226],"iteration":851,"passed_time":3704.431156,"remaining_time":643.492736},
{"learn":[0.3093519255],"iteration":852,"passed_time":3708.904867,"remaining_time":639.1664894},
{"learn":[0.3093157544],"iteration":853,"passed_time":3713.677779,"remaining_time":634.8910489},
{"learn":[0.3091960516],"iteration":854,"passed_time":3717.897306,"remaining_time":630.5205957},
{"learn":[0.3091518686],"iteration":855,"passed_time":3722.528696,"remaining_time":626.2197806},
{"learn":[0.3090805908],"iteration":856,"passed_time":3728.748837,"remaining_time":622.1832948},
{"learn":[0.3089568505],"iteration":857,"passed_time":3734.492128,"remaining_time":618.0627997},
{"learn":[0.3088582996],"iteration":858,"passed_time":3739.988292,"remaining_time":613.8979618},
{"learn":[0.3087921949],"iteration":859,"passed_time":3743.95942,"remaining_time":609.481766},
{"learn":[0.3087669571],"iteration":860,"passed_time":3747.485001,"remaining_time":604.994675},
{"learn":[0.3086641732],"iteration":861,"passed_time":3751.961227,"remaining_time":600.6620062},
{"learn":[0.3084967874],"iteration":862,"passed_time":3756.507965,"remaining_time":596.3401984},
{"learn":[0.3084140618],"iteration":863,"passed_time":3760.846849,"remaining_time":591.9851522},
{"learn":[0.3083615056],"iteration":864,"passed_time":3765.448099,"remaining_time":587.6710906},
{"learn":[0.3082706249],"iteration":865,"passed_time":3769.598851,"remaining_time":583.2866582},
{"learn":[0.3082291659],"iteration":866,"passed_time":3774.185215,"remaining_time":578.9695889},
{"learn":[0.3081808248],"iteration":867,"passed_time":3779.593784,"remaining_time":574.7769348},
{"learn":[0.3081155615],"iteration":868,"passed_time":3784.189121,"remaining_time":570.4588894},
{"learn":[0.3080454166],"iteration":869,"passed_time":3790.118394,"remaining_time":566.3395302},
{"learn":[0.3079499644],"iteration":870,"passed_time":3795.893955,"remaining_time":562.1932494},
{"learn":[0.307907723],"iteration":871,"passed_time":3801.623546,"remaining_time":558.0364839},
{"learn":[0.3078544955],"iteration":872,"passed_time":3807.161005,"remaining_time":553.8481646},
{"learn":[0.3078153687],"iteration":873,"passed_time":3812.547966,"remaining_time":549.6350614},
{"learn":[0.3076861818],"iteration":874,"passed_time":3817.527337,"remaining_time":545.3610482},
{"learn":[0.3076123994],"iteration":875,"passed_time":3822.868397,"remaining_time":541.1366224},
{"learn":[0.3075332343],"iteration":876,"passed_time":3827.889359,"remaining_time":536.8647562},
{"learn":[0.3074899051],"iteration":877,"passed_time":3833.242322,"remaining_time":532.6373159},
{"learn":[0.307397242],"iteration":878,"passed_time":3839.150647,"remaining_time":528.4837637},
{"learn":[0.3073468205],"iteration":879,"passed_time":3843.917128,"remaining_time":524.1705175},
{"learn":[0.3072949774],"iteration":880,"passed_time":3848.908036,"remaining_time":519.8865565},
{"learn":[0.3072111587],"iteration":881,"passed_time":3853.533887,"remaining_time":515.5521527},
{"learn":[0.3070000624],"iteration":882,"passed_time":3858.64191,"remaining_time":511.2809779},
{"learn":[0.3069420947],"iteration":883,"passed_time":3864.51879,"remaining_time":507.1088005},
{"learn":[0.3068928879],"iteration":884,"passed_time":3869.419174,"remaining_time":502.8058813},
{"learn":[0.3068645286],"iteration":885,"passed_time":3873.752091,"remaining_time":498.4285986},
{"learn":[0.3068272663],"iteration":886,"passed_time":3880.014902,"remaining_time":494.2972761},
{"learn":[0.3067947294],"iteration":887,"passed_time":3885.792807,"remaining_time":490.0999937},
{"learn":[0.306651954],"iteration":888,"passed_time":3890.915083,"remaining_time":485.8172939},
{"learn":[0.3065424921],"iteration":889,"passed_time":3895.43079,"remaining_time":481.457738},
{"learn":[0.3064359459],"iteration":890,"passed_time":3900.322425,"remaining_time":477.1438208},
{"learn":[0.306357265],"iteration":891,"passed_time":3904.479705,"remaining_time":472.7396953},
{"learn":[0.3062487005],"iteration":892,"passed_time":3909.410953,"remaining_time":468.42886},
{"learn":[0.3062198539],"iteration":893,"passed_time":3914.744675,"remaining_time":464.1643574},
{"learn":[0.3061591501],"iteration":894,"passed_time":3920.206411,"remaining_time":459.912484},
{"learn":[0.3060281499],"iteration":895,"passed_time":3924.805297,"remaining_time":455.5577577},
{"learn":[0.3059727586],"iteration":896,"passed_time":3928.539274,"remaining_time":451.103172},
{"learn":[0.3058162783],"iteration":897,"passed_time":3932.428039,"remaining_time":446.6677729},
{"learn":[0.3058023277],"iteration":898,"passed_time":3936.711986,"remaining_time":442.2779873},
{"learn":[0.3056832375],"iteration":899,"passed_time":3940.718385,"remaining_time":437.8575983},
{"learn":[0.3056044947],"iteration":900,"passed_time":3945.648097,"remaining_time":433.53958},
{"learn":[0.3055778026],"iteration":901,"passed_time":3949.61742,"remaining_time":429.1158616},
{"learn":[0.3055462824],"iteration":902,"passed_time":3954.073223,"remaining_time":424.7454071},
{"learn":[0.3055017096],"iteration":903,"passed_time":3960.477346,"remaining_time":420.581665},
{"learn":[0.3053947212],"iteration":904,"passed_time":3965.711534,"remaining_time":416.290161},
{"learn":[0.3053548909],"iteration":905,"passed_time":3972.187403,"remaining_time":412.1254038},
{"learn":[0.3051015472],"iteration":906,"passed_time":3977.033846,"remaining_time":407.7884759},
{"learn":[0.3049942454],"iteration":907,"passed_time":3982.060041,"remaining_time":403.4686385},
{"learn":[0.3049421546],"iteration":908,"passed_time":3986.334232,"remaining_time":399.0719638},
{"learn":[0.3048189621],"iteration":909,"passed_time":3990.731898,"remaining_time":394.6877701},
{"learn":[0.3046983892],"iteration":910,"passed_time":3994.857135,"remaining_time":390.276932},
{"learn":[0.3046271589],"iteration":911,"passed_time":3999.099718,"remaining_time":385.878043},
{"learn":[0.3045384189],"iteration":912,"passed_time":4003.832569,"remaining_time":381.5262141},
{"learn":[0.304518189],"iteration":913,"passed_time":4008.159982,"remaining_time":377.1354031},
{"learn":[0.3044198751],"iteration":914,"passed_time":4013.190431,"remaining_time":372.8100401},
{"learn":[0.3042372392],"iteration":915,"passed_time":4017.450771,"remaining_time":368.4125161},
{"learn":[0.3041490322],"iteration":916,"passed_time":4021.654946,"remaining_time":364.0102078},
{"learn":[0.3041254872],"iteration":917,"passed_time":4026.718966,"remaining_time":359.6851364},
{"learn":[0.3039538727],"iteration":918,"passed_time":4030.714358,"remaining_time":355.2642688},
{"learn":[0.3039367709],"iteration":919,"passed_time":4035.792383,"remaining_time":350.938468},
{"learn":[0.3037255753],"iteration":920,"passed_time":4040.094705,"remaining_time":346.5444969},
{"learn":[0.3036412342],"iteration":921,"passed_time":4044.185929,"remaining_time":342.132866},
{"learn":[0.3035970295],"iteration":922,"passed_time":4048.407466,"remaining_time":337.7328006},
{"learn":[0.3033720268],"iteration":923,"passed_time":4052.847629,"remaining_time":333.3511037},
{"learn":[0.3033594053],"iteration":924,"passed_time":4057.110031,"remaining_time":328.9548674},
{"learn":[0.3032517258],"iteration":925,"passed_time":4062.054037,"remaining_time":324.6133895},
{"learn":[0.3031455853],"iteration":926,"passed_time":4066.505872,"remaining_time":320.231854},
{"learn":[0.303090694],"iteration":927,"passed_time":4070.255674,"remaining_time":315.7956989},
{"learn":[0.3030198109],"iteration":928,"passed_time":4075.063713,"remaining_time":311.4418984},
{"learn":[0.3029738565],"iteration":929,"passed_time":4079.329682,"remaining_time":307.0463202},
{"learn":[0.3028473497],"iteration":930,"passed_time":4084.430283,"remaining_time":302.7128781},
{"learn":[0.3026457603],"iteration":931,"passed_time":4088.706258,"remaining_time":298.317624},
{"learn":[0.3025303993],"iteration":932,"passed_time":4093.381845,"remaining_time":293.9513222},
{"learn":[0.3024899342],"iteration":933,"passed_time":4097.882814,"remaining_time":289.5720189},
{"learn":[0.3024430459],"iteration":934,"passed_time":4103.080266,"remaining_time":285.2408741},
{"learn":[0.3022027597],"iteration":935,"passed_time":4107.801169,"remaining_time":280.8752936},
{"learn":[0.3021232103],"iteration":936,"passed_time":4112.287518,"remaining_time":276.4931843},
{"learn":[0.3019255796],"iteration":937,"passed_time":4116.756871,"remaining_time":272.1097292},
{"learn":[0.3018474496],"iteration":938,"passed_time":4121.171917,"remaining_time":267.7225633},
{"learn":[0.3017453723],"iteration":939,"passed_time":4126.505756,"remaining_time":263.3939844},
{"learn":[0.3017053283],"iteration":940,"passed_time":4132.303196,"remaining_time":259.0923364},
{"learn":[0.3016422389],"iteration":941,"passed_time":4138.505752,"remaining_time":254.8124561},
{"learn":[0.3015402686],"iteration":942,"passed_time":4143.979028,"remaining_time":250.4844163},
{"learn":[0.3014891865],"iteration":943,"passed_time":4150.666906,"remaining_time":246.2260029},
{"learn":[0.3014352386],"iteration":944,"passed_time":4155.615555,"remaining_time":241.8612228},
{"learn":[0.3013871563],"iteration":945,"passed_time":4159.534594,"remaining_time":237.4364356},
{"learn":[0.301359481],"iteration":946,"passed_time":4164.199198,"remaining_time":233.054443},
{"learn":[0.3013191173],"iteration":947,"passed_time":4169.0851,"remaining_time":228.6839928},
{"learn":[0.3012317458],"iteration":948,"passed_time":4173.679053,"remaining_time":224.2967668},
{"learn":[0.3011968187],"iteration":949,"passed_time":4177.922337,"remaining_time":219.8906493},
{"learn":[0.3011828678],"iteration":950,"passed_time":4182.809343,"remaining_time":215.5180419},
{"learn":[0.3011196668],"iteration":951,"passed_time":4186.83668,"remaining_time":211.1010091},
{"learn":[0.3010975152],"iteration":952,"passed_time":4191.678673,"remaining_time":206.7249713},
{"learn":[0.3010351897],"iteration":953,"passed_time":4195.689588,"remaining_time":202.3078837},
{"learn":[0.3008685563],"iteration":954,"passed_time":4199.390061,"remaining_time":197.8770186},
{"learn":[0.3007517523],"iteration":955,"passed_time":4204.709308,"remaining_time":193.5221857},
{"learn":[0.3006341854],"iteration":956,"passed_time":4208.836016,"remaining_time":189.1117541},
{"learn":[0.3004589928],"iteration":957,"passed_time":4213.402936,"remaining_time":184.7212143},
{"learn":[0.3004095372],"iteration":958,"passed_time":4218.32248,"remaining_time":180.3453824},
{"learn":[0.3003026904],"iteration":959,"passed_time":4222.950771,"remaining_time":175.9562821},
{"learn":[0.3002424753],"iteration":960,"passed_time":4226.888433,"remaining_time":171.5386565},
{"learn":[0.3002118761],"iteration":961,"passed_time":4231.752187,"remaining_time":167.1586103},
{"learn":[0.3000001101],"iteration":962,"passed_time":4236.520952,"remaining_time":162.7739099},
{"learn":[0.2999023037],"iteration":963,"passed_time":4240.458202,"remaining_time":158.3573602},
{"learn":[0.2998650253],"iteration":964,"passed_time":4245.091689,"remaining_time":153.9670561},
{"learn":[0.2997413634],"iteration":965,"passed_time":4249.71685,"remaining_time":149.5759554},
{"learn":[0.2997162866],"iteration":966,"passed_time":4254.717022,"remaining_time":145.1971683},
{"learn":[0.299696444],"iteration":967,"passed_time":4258.744845,"remaining_time":140.7849535},
{"learn":[0.2996610354],"iteration":968,"passed_time":4263.853421,"remaining_time":136.4081074},
{"learn":[0.2995855138],"iteration":969,"passed_time":4268.218394,"remaining_time":132.0067545},
{"learn":[0.2995057713],"iteration":970,"passed_time":4272.220172,"remaining_time":127.5946292},
{"learn":[0.2994436934],"iteration":971,"passed_time":4277.495906,"remaining_time":123.2200467},
{"learn":[0.2993496936],"iteration":972,"passed_time":4281.484826,"remaining_time":118.8079037},
{"learn":[0.2993328419],"iteration":973,"passed_time":4285.293595,"remaining_time":114.3918208},
{"learn":[0.2991928832],"iteration":974,"passed_time":4290.384771,"remaining_time":110.0098659},
{"learn":[0.2991437935],"iteration":975,"passed_time":4295.041831,"remaining_time":105.6157827},
{"learn":[0.2990874639],"iteration":976,"passed_time":4299.527372,"remaining_time":101.2171234},
{"learn":[0.2990747818],"iteration":977,"passed_time":4303.684213,"remaining_time":96.81089232},
{"learn":[0.2990109738],"iteration":978,"passed_time":4308.698531,"remaining_time":92.423564},
{"learn":[0.2989892219],"iteration":979,"passed_time":4313.457249,"remaining_time":88.02973977},
{"learn":[0.2989398065],"iteration":980,"passed_time":4318.550881,"remaining_time":83.64165825},
{"learn":[0.2988878717],"iteration":981,"passed_time":4323.280643,"remaining_time":79.24547003},
{"learn":[0.2987896068],"iteration":982,"passed_time":4327.739267,"remaining_time":74.84391408},
{"learn":[0.298583846],"iteration":983,"passed_time":4332.65633,"remaining_time":70.44969642},
{"learn":[0.298537483],"iteration":984,"passed_time":4337.346123,"remaining_time":66.05095618},
{"learn":[0.2985052804],"iteration":985,"passed_time":4342.046704,"remaining_time":61.65177877},
{"learn":[0.2984600245],"iteration":986,"passed_time":4347.117768,"remaining_time":57.2568703},
{"learn":[0.2983530482],"iteration":987,"passed_time":4350.674289,"remaining_time":52.84219784},
{"learn":[0.2982612381],"iteration":988,"passed_time":4355.544666,"remaining_time":48.44387394},
{"learn":[0.2982195387],"iteration":989,"passed_time":4360.301463,"remaining_time":44.04344912},
{"learn":[0.2981956278],"iteration":990,"passed_time":4364.191,"remaining_time":39.63442886},
{"learn":[0.2981481302],"iteration":991,"passed_time":4369.217093,"remaining_time":35.23562171},
{"learn":[0.2981030305],"iteration":992,"passed_time":4373.315343,"remaining_time":30.82901047},
{"learn":[0.2980366957],"iteration":993,"passed_time":4377.862228,"remaining_time":26.42572773},
{"learn":[0.2980120921],"iteration":994,"passed_time":4382.763669,"remaining_time":22.02393803},
{"learn":[0.2979841705],"iteration":995,"passed_time":4387.148141,"remaining_time":17.61906884},
{"learn":[0.2979590443],"iteration":996,"passed_time":4390.959025,"remaining_time":13.21251462},
{"learn":[0.2979290089],"iteration":997,"passed_time":4397.786327,"remaining_time":8.813199051},
{"learn":[0.2978516631],"iteration":998,"passed_time":4403.299799,"remaining_time":4.407707507},
{"learn":[0.2977931101],"iteration":999,"passed_time":4409.538925,"remaining_time":0}
]}